{"url":"https://www.cardecsxm.com/","requestedUrl":"https://www.cardecsxm.com/","timestamp":1598810551148,"ranks":{"hundos":53,"performance":71,"accessibility":40,"cumulative":53},"lighthouse":{"version":"6.3.0","performance":0.34,"accessibility":0.9,"bestPractices":0.79,"seo":0.98,"total":301,"carbon":"0.0639"},"firstContentfulPaint":3944.3860000000004,"speedIndex":6306.036117911717,"largestContentfulPaint":6508.967000000001,"totalBlockingTime":982.5,"cumulativeLayoutShift":0.15301200358072917,"timeToInteractive":6439.577000000001,"maxPotentialFirstInputDelay":305,"timeToFirstByte":857.04,"weight":{"summary":"80 requests • 1,117 KiB","total":1143910,"image":618651,"imageCount":22,"script":363517,"scriptCount":22,"document":31233,"font":48263,"fontCount":6,"stylesheet":81951,"stylesheetCount":26,"thirdParty":234225,"thirdPartyCount":18},"axe":{"passes":641,"violations":63}}