{"url":"https://doshas-consulting.com/","requestedUrl":"https://doshas-consulting.com/","timestamp":1598827975479,"ranks":{"hundos":117,"performance":168,"accessibility":52,"cumulative":118},"lighthouse":{"version":"6.3.0","performance":0.38,"accessibility":0.95,"bestPractices":0.71,"seo":1,"total":304,"carbon":"0.224"},"firstContentfulPaint":3970.6149999999993,"speedIndex":15670.266486981836,"largestContentfulPaint":8466.752499999999,"totalBlockingTime":249,"cumulativeLayoutShift":0.17979905870225696,"timeToInteractive":10950.037499999997,"maxPotentialFirstInputDelay":227,"timeToFirstByte":4072.6740000000004,"weight":{"summary":"131 requests • 3,913 KiB","total":4007281,"image":3385053,"imageCount":78,"script":347134,"scriptCount":29,"document":16105,"font":138354,"fontCount":6,"stylesheet":119944,"stylesheetCount":13,"thirdParty":1144973,"thirdPartyCount":62},"axe":{"passes":689,"violations":43}}