{"url":"https://www.neillschool.com/","requestedUrl":"http://www.neillschool.com/","timestamp":1598872819663,"ranks":{"hundos":97,"performance":115,"accessibility":96,"cumulative":96},"lighthouse":{"version":"6.3.0","performance":0.25,"accessibility":0.79,"bestPractices":0.64,"seo":1,"total":268,"carbon":"0.120"},"firstContentfulPaint":3801.171,"speedIndex":7294.269341555597,"largestContentfulPaint":10540.015500000001,"totalBlockingTime":877.4999999999995,"cumulativeLayoutShift":0.2983194173177083,"timeToInteractive":10157.345000000001,"maxPotentialFirstInputDelay":456,"timeToFirstByte":725.49,"weight":{"summary":"112 requests • 2,093 KiB","total":2143657,"image":1252227,"imageCount":43,"script":620103,"scriptCount":34,"document":26017,"font":166871,"fontCount":9,"stylesheet":78085,"stylesheetCount":23,"thirdParty":1277293,"thirdPartyCount":58},"axe":{"passes":951,"violations":26}}