{"url":"https://thekingofvillas.com/","requestedUrl":"https://thekingofvillas.com/","timestamp":1598804392897,"ranks":{"hundos":95,"performance":88,"accessibility":84,"cumulative":94},"lighthouse":{"version":"6.3.0","performance":0.15,"accessibility":0.75,"bestPractices":0.57,"seo":0.92,"total":239,"carbon":"0.139"},"firstContentfulPaint":5611.4230000000025,"speedIndex":7492.956818289001,"largestContentfulPaint":10506.950500000003,"totalBlockingTime":1600.0000000000036,"cumulativeLayoutShift":0.0046394856770833335,"timeToInteractive":13941.390500000005,"maxPotentialFirstInputDelay":430.0000000000018,"timeToFirstByte":359.49699999999996,"weight":{"summary":"94 requests • 2,432 KiB","total":2489905,"image":1609283,"imageCount":37,"script":503986,"scriptCount":25,"document":28616,"font":201817,"fontCount":6,"stylesheet":143752,"stylesheetCount":18,"thirdParty":561606,"thirdPartyCount":35},"axe":{"passes":622,"violations":65}}