[{"url":"https://www.roc-nijmegen.nl/","requestedUrl":"https://www.roc-nijmegen.nl/","timestamp":1598811134775,"ranks":{"hundos":1,"performance":11,"accessibility":2,"cumulative":1},"lighthouse":{"version":"6.3.0","performance":0.86,"accessibility":0.98,"bestPractices":1,"seo":0.99,"total":383,"carbon":"0.0241"},"firstContentfulPaint":1766.1099999999997,"speedIndex":2710.2841259111547,"largestContentfulPaint":3189.6389999999997,"totalBlockingTime":368.5,"cumulativeLayoutShift":0.0007655029296875001,"timeToInteractive":3683.665,"maxPotentialFirstInputDelay":307,"timeToFirstByte":271.91100000000006,"weight":{"summary":"17 requests • 421 KiB","total":430929,"image":152172,"imageCount":3,"script":147506,"scriptCount":7,"document":10656,"font":0,"fontCount":0,"stylesheet":17222,"stylesheetCount":1,"thirdParty":94149,"thirdPartyCount":7},"axe":{"passes":739,"violations":2}},{"url":"https://www.bybusa.com/","requestedUrl":"https://www.bybusa.com/","timestamp":1598811268028,"ranks":{"hundos":2,"performance":5,"accessibility":72,"cumulative":2},"lighthouse":{"version":"6.3.0","performance":0.92,"accessibility":0.83,"bestPractices":0.93,"seo":0.99,"total":367,"carbon":"0.0377"},"firstContentfulPaint":1557.7649999999996,"speedIndex":3914.1210898151894,"largestContentfulPaint":2028.7889999999998,"totalBlockingTime":248.49999999999955,"cumulativeLayoutShift":0.06618584526909722,"timeToInteractive":4522.525,"maxPotentialFirstInputDelay":381.9999999999991,"timeToFirstByte":884.096,"weight":{"summary":"29 requests • 660 KiB","total":675543,"image":307619,"imageCount":18,"script":270433,"scriptCount":6,"document":17759,"font":9642,"fontCount":1,"stylesheet":69130,"stylesheetCount":1,"thirdParty":85998,"thirdPartyCount":6},"axe":{"passes":1907,"violations":306}},{"url":"https://www.inpersona.net/de/","requestedUrl":"https://www.inpersona.net/","timestamp":1598809868065,"ranks":{"hundos":3,"performance":7,"accessibility":14,"cumulative":3},"lighthouse":{"version":"6.3.0","performance":0.89,"accessibility":0.95,"bestPractices":0.86,"seo":0.96,"total":366,"carbon":"0.0104"},"firstContentfulPaint":2735.591,"speedIndex":4454.739646005521,"largestContentfulPaint":2735.591,"totalBlockingTime":6.5,"cumulativeLayoutShift":0.00115966796875,"timeToInteractive":2788.591,"maxPotentialFirstInputDelay":63,"timeToFirstByte":459.18699999999995,"weight":{"summary":"21 requests • 182 KiB","total":186123,"image":36080,"imageCount":14,"script":121660,"scriptCount":1,"document":11715,"font":0,"fontCount":0,"stylesheet":15466,"stylesheetCount":2,"thirdParty":1244,"thirdPartyCount":1},"axe":{"passes":626,"violations":7}},{"url":"https://www.salera-restaurant.de/","requestedUrl":"https://www.salera-restaurant.de/","timestamp":1598810128684,"ranks":{"hundos":4,"performance":9,"accessibility":30,"cumulative":4},"lighthouse":{"version":"6.3.0","performance":0.88,"accessibility":0.91,"bestPractices":0.86,"seo":1,"total":365,"carbon":"0.0199"},"firstContentfulPaint":2245.1,"speedIndex":3834.6745769308895,"largestContentfulPaint":3399.2704999999996,"totalBlockingTime":57.5,"cumulativeLayoutShift":0.027934299045138892,"timeToInteractive":2886.6929999999998,"maxPotentialFirstInputDelay":124,"timeToFirstByte":245.29500000000002,"weight":{"summary":"16 requests • 348 KiB","total":355867,"image":120025,"imageCount":3,"script":141639,"scriptCount":8,"document":7442,"font":41182,"fontCount":2,"stylesheet":45579,"stylesheetCount":2,"thirdParty":40177,"thirdPartyCount":1},"axe":{"passes":361,"violations":12}},{"url":"https://www.scope.ch/de/","requestedUrl":"https://www.scope.ch/","timestamp":1598809858875,"ranks":{"hundos":5,"performance":12,"accessibility":7,"cumulative":5},"lighthouse":{"version":"6.3.0","performance":0.81,"accessibility":0.97,"bestPractices":0.86,"seo":0.99,"total":363,"carbon":"0.0318"},"firstContentfulPaint":2740.81,"speedIndex":4240.841986693416,"largestContentfulPaint":3954.65,"totalBlockingTime":53.5,"cumulativeLayoutShift":0.00017626953125,"timeToInteractive":3019.194,"maxPotentialFirstInputDelay":157,"timeToFirstByte":266.54400000000004,"weight":{"summary":"45 requests • 555 KiB","total":568704,"image":373096,"imageCount":22,"script":155911,"scriptCount":13,"document":11729,"font":0,"fontCount":0,"stylesheet":27530,"stylesheetCount":8,"thirdParty":1508,"thirdPartyCount":1},"axe":{"passes":340,"violations":44}},{"url":"https://wheelworxinc.com/","requestedUrl":"https://wheelworxinc.com/","timestamp":1598811846917,"ranks":{"hundos":6,"performance":14,"accessibility":5,"cumulative":6},"lighthouse":{"version":"6.3.0","performance":0.77,"accessibility":0.97,"bestPractices":0.86,"seo":1,"total":360,"carbon":"0.0296"},"firstContentfulPaint":2339.422,"speedIndex":3129.9139961770343,"largestContentfulPaint":4802.4205,"totalBlockingTime":57.28899999999999,"cumulativeLayoutShift":0.243466796875,"timeToInteractive":2931.422,"maxPotentialFirstInputDelay":175.5,"timeToFirstByte":519.961,"weight":{"summary":"25 requests • 517 KiB","total":529450,"image":173706,"imageCount":4,"script":193150,"scriptCount":11,"document":10039,"font":83524,"fontCount":4,"stylesheet":68824,"stylesheetCount":4,"thirdParty":55389,"thirdPartyCount":3},"axe":{"passes":273,"violations":11}},{"url":"https://www.google.es/","requestedUrl":"https://google.es/","timestamp":1598811667959,"ranks":{"hundos":7,"performance":8,"accessibility":36,"cumulative":7},"lighthouse":{"version":"6.3.0","performance":0.88,"accessibility":0.9,"bestPractices":0.93,"seo":0.85,"total":356,"carbon":"0.0235"},"firstContentfulPaint":1748.98,"speedIndex":1748.98,"largestContentfulPaint":1943.8575,"totalBlockingTime":448.5,"cumulativeLayoutShift":0,"timeToInteractive":4921.3875,"maxPotentialFirstInputDelay":266,"timeToFirstByte":76.307,"weight":{"summary":"24 requests • 411 KiB","total":420660,"image":18314,"imageCount":14,"script":359283,"scriptCount":5,"document":39557,"font":0,"fontCount":0,"stylesheet":3074,"stylesheetCount":1,"thirdParty":104058,"thirdPartyCount":12},"axe":{"passes":233,"violations":13}},{"url":"https://www.watisdaaropjeantwoord.nl/","requestedUrl":"https://www.watisdaaropjeantwoord.nl/","timestamp":1598810205650,"ranks":{"hundos":8,"performance":13,"accessibility":6,"cumulative":8},"lighthouse":{"version":"6.3.0","performance":0.8,"accessibility":0.97,"bestPractices":0.79,"seo":1,"total":356,"carbon":"0.0503"},"firstContentfulPaint":2778.1979999999994,"speedIndex":4657.708260459756,"largestContentfulPaint":3481.2079999999996,"totalBlockingTime":79,"cumulativeLayoutShift":0.1853504638671875,"timeToInteractive":4148.449999999999,"maxPotentialFirstInputDelay":126,"timeToFirstByte":406.018,"weight":{"summary":"41 requests • 879 KiB","total":900440,"image":590332,"imageCount":7,"script":78375,"scriptCount":11,"document":7799,"font":142293,"fontCount":5,"stylesheet":81641,"stylesheetCount":17,"thirdParty":70487,"thirdPartyCount":9},"axe":{"passes":346,"violations":21}},{"url":"https://lewiscountyep.com/","requestedUrl":"https://lewiscountyep.com/","timestamp":1598810242494,"ranks":{"hundos":9,"performance":21,"accessibility":29,"cumulative":9},"lighthouse":{"version":"6.3.0","performance":0.7,"accessibility":0.91,"bestPractices":0.93,"seo":1,"total":354,"carbon":"0.0699"},"firstContentfulPaint":2457.221,"speedIndex":4254.189457294489,"largestContentfulPaint":3421.4219999999996,"totalBlockingTime":454,"cumulativeLayoutShift":0.0228167724609375,"timeToInteractive":8256.178499999998,"maxPotentialFirstInputDelay":198,"timeToFirstByte":752.651,"weight":{"summary":"63 requests • 1,222 KiB","total":1251031,"image":386657,"imageCount":17,"script":688615,"scriptCount":26,"document":26490,"font":39106,"fontCount":2,"stylesheet":89940,"stylesheetCount":12,"thirdParty":745857,"thirdPartyCount":48},"axe":{"passes":128,"violations":4}},{"url":"https://www.survivinginbrussels.be/app/fr/","requestedUrl":"https://www.survivinginbrussels.be/","timestamp":1598811824216,"ranks":{"hundos":10,"performance":4,"accessibility":89,"cumulative":10},"lighthouse":{"version":"6.3.0","performance":0.93,"accessibility":0.73,"bestPractices":0.86,"seo":1,"total":352,"carbon":"0.0259"},"firstContentfulPaint":1856.221,"speedIndex":3851.386298000025,"largestContentfulPaint":1931.221,"totalBlockingTime":3,"cumulativeLayoutShift":0.34756754557291664,"timeToInteractive":2012.221,"maxPotentialFirstInputDelay":56,"timeToFirstByte":345.358,"weight":{"summary":"50 requests • 452 KiB","total":463143,"image":226117,"imageCount":35,"script":30491,"scriptCount":6,"document":6398,"font":187516,"fontCount":2,"stylesheet":12098,"stylesheetCount":5,"thirdParty":0,"thirdPartyCount":0},"axe":{"passes":258,"violations":3}},{"url":"https://www.rechtsanwalt-reents.de/","requestedUrl":"https://www.rechtsanwalt-reents.de/","timestamp":1598811201062,"ranks":{"hundos":11,"performance":17,"accessibility":8,"cumulative":11},"lighthouse":{"version":"6.3.0","performance":0.75,"accessibility":0.96,"bestPractices":0.86,"seo":0.94,"total":351,"carbon":"0.0333"},"firstContentfulPaint":2133.29,"speedIndex":4702.970470811853,"largestContentfulPaint":4608.29,"totalBlockingTime":155.35500000000002,"cumulativeLayoutShift":0.17201649305555555,"timeToInteractive":3478.29,"maxPotentialFirstInputDelay":150,"timeToFirstByte":651.674,"weight":{"summary":"40 requests • 582 KiB","total":595581,"image":121158,"imageCount":6,"script":173638,"scriptCount":9,"document":18097,"font":213606,"fontCount":10,"stylesheet":68894,"stylesheetCount":13,"thirdParty":0,"thirdPartyCount":0},"axe":{"passes":357,"violations":7}},{"url":"https://feminapt.com/","requestedUrl":"https://feminapt.com/","timestamp":1598812909973,"ranks":{"hundos":12,"performance":1,"accessibility":70,"cumulative":12},"lighthouse":{"version":"6.3.0","performance":0.97,"accessibility":0.84,"bestPractices":0.93,"seo":0.75,"total":349,"carbon":"0.0487"},"firstContentfulPaint":1605.629,"speedIndex":1740.5449139997374,"largestContentfulPaint":1919.3069999999998,"totalBlockingTime":40.5,"cumulativeLayoutShift":0,"timeToInteractive":4139.648499999999,"maxPotentialFirstInputDelay":106,"timeToFirstByte":64.17700000000002,"weight":{"summary":"31 requests • 852 KiB","total":872271,"image":725170,"imageCount":20,"script":108143,"scriptCount":9,"document":38958,"font":0,"fontCount":0,"stylesheet":0,"stylesheetCount":1,"thirdParty":19270,"thirdPartyCount":4},"axe":{"passes":1495,"violations":71}},{"url":"https://www.scibio.eu/","requestedUrl":"https://www.scibio.eu/","timestamp":1598811143010,"ranks":{"hundos":13,"performance":19,"accessibility":3,"cumulative":13},"lighthouse":{"version":"6.3.0","performance":0.73,"accessibility":0.98,"bestPractices":0.79,"seo":0.98,"total":348,"carbon":"0.0444"},"firstContentfulPaint":2684.534,"speedIndex":4338.756415667599,"largestContentfulPaint":4149.9,"totalBlockingTime":91.5,"cumulativeLayoutShift":0.5622392306857639,"timeToInteractive":4737.8150000000005,"maxPotentialFirstInputDelay":105,"timeToFirstByte":978.056,"weight":{"summary":"30 requests • 776 KiB","total":794940,"image":434251,"imageCount":13,"script":173766,"scriptCount":6,"document":6509,"font":117155,"fontCount":4,"stylesheet":63171,"stylesheetCount":5,"thirdParty":142348,"thirdPartyCount":8},"axe":{"passes":344,"violations":2}},{"url":"https://www.project3architects.com/","requestedUrl":"https://www.project3architects.com/","timestamp":1598810999324,"ranks":{"hundos":14,"performance":28,"accessibility":4,"cumulative":14},"lighthouse":{"version":"6.3.0","performance":0.63,"accessibility":0.97,"bestPractices":0.93,"seo":0.92,"total":345,"carbon":"0.191"},"firstContentfulPaint":4619.8975,"speedIndex":4930.0623584380255,"largestContentfulPaint":5004.393,"totalBlockingTime":190,"cumulativeLayoutShift":0.001535305447048611,"timeToInteractive":5147.317999999999,"maxPotentialFirstInputDelay":430,"timeToFirstByte":203.87000000000003,"weight":{"summary":"36 requests • 3,345 KiB","total":3425113,"image":2988060,"imageCount":13,"script":190556,"scriptCount":11,"document":6356,"font":100629,"fontCount":3,"stylesheet":139512,"stylesheetCount":8,"thirdParty":3418757,"thirdPartyCount":35},"axe":{"passes":113,"violations":7}},{"url":"https://anaishas.com/","requestedUrl":"https://anaishas.com/","timestamp":1598811190495,"ranks":{"hundos":15,"performance":31,"accessibility":15,"cumulative":15},"lighthouse":{"version":"6.3.0","performance":0.6,"accessibility":0.95,"bestPractices":0.86,"seo":1,"total":341,"carbon":"0.201"},"firstContentfulPaint":2283.9990000000003,"speedIndex":4223.919632528131,"largestContentfulPaint":7979.5960000000005,"totalBlockingTime":195,"cumulativeLayoutShift":0.7241227213541667,"timeToInteractive":6074.263999999999,"maxPotentialFirstInputDelay":166,"timeToFirstByte":495.905,"weight":{"summary":"45 requests • 3,509 KiB","total":3593442,"image":2955032,"imageCount":16,"script":573857,"scriptCount":15,"document":6024,"font":10967,"fontCount":1,"stylesheet":47562,"stylesheetCount":12,"thirdParty":509716,"thirdPartyCount":7},"axe":{"passes":251,"violations":17}},{"url":"https://mrguitarlessons.com/","requestedUrl":"https://mrguitarlessons.com/","timestamp":1598809280762,"ranks":{"hundos":16,"performance":32,"accessibility":24,"cumulative":16},"lighthouse":{"version":"6.3.0","performance":0.59,"accessibility":0.93,"bestPractices":0.86,"seo":1,"total":338,"carbon":"0.120"},"firstContentfulPaint":2179.598,"speedIndex":4494.248984142661,"largestContentfulPaint":10257.587999999998,"totalBlockingTime":468.9999999999998,"cumulativeLayoutShift":0.002509521484375,"timeToInteractive":4827.8225,"maxPotentialFirstInputDelay":296,"timeToFirstByte":552.1270000000001,"weight":{"summary":"21 requests • 2,103 KiB","total":2153197,"image":1641478,"imageCount":9,"script":151842,"scriptCount":4,"document":21823,"font":307216,"fontCount":6,"stylesheet":30838,"stylesheetCount":1,"thirdParty":108237,"thirdPartyCount":6},"axe":{"passes":357,"violations":10}},{"url":"https://www.oinvertebrado.com/","requestedUrl":"https://www.oinvertebrado.com/","timestamp":1598810442415,"ranks":{"hundos":17,"performance":20,"accessibility":22,"cumulative":17},"lighthouse":{"version":"6.3.0","performance":0.72,"accessibility":0.94,"bestPractices":0.79,"seo":0.92,"total":337,"carbon":"0.0150"},"firstContentfulPaint":2970.4339999999997,"speedIndex":5649.842200287374,"largestContentfulPaint":3888.6020000000008,"totalBlockingTime":207.99999999999977,"cumulativeLayoutShift":0.2987750244140625,"timeToInteractive":3814.8100000000004,"maxPotentialFirstInputDelay":406.99999999999955,"timeToFirstByte":593.792,"weight":{"summary":"28 requests • 262 KiB","total":268786,"image":104149,"imageCount":13,"script":46566,"scriptCount":4,"document":21669,"font":66910,"fontCount":1,"stylesheet":29492,"stylesheetCount":9,"thirdParty":73392,"thirdPartyCount":2},"axe":{"passes":497,"violations":34}},{"url":"https://artglassandmetal.com/","requestedUrl":"https://artglassandmetal.com/","timestamp":1598809821398,"ranks":{"hundos":18,"performance":15,"accessibility":74,"cumulative":18},"lighthouse":{"version":"6.3.0","performance":0.77,"accessibility":0.82,"bestPractices":0.86,"seo":0.92,"total":337,"carbon":"0.0317"},"firstContentfulPaint":1297.8870000000002,"speedIndex":3209.366975124344,"largestContentfulPaint":4185.259,"totalBlockingTime":248.67799999999943,"cumulativeLayoutShift":0.33569444444444446,"timeToInteractive":4739.869000000001,"maxPotentialFirstInputDelay":348,"timeToFirstByte":62.24599999999998,"weight":{"summary":"22 requests • 618 KiB","total":567210,"image":208010,"imageCount":7,"script":201268,"scriptCount":8,"document":20609,"font":152012,"fontCount":5,"stylesheet":51029,"stylesheetCount":1,"thirdParty":88051,"thirdPartyCount":7},"axe":{"passes":619,"violations":66}},{"url":"https://www.sbcalliance.org/","requestedUrl":"https://www.sbcalliance.org/","timestamp":1598810626885,"ranks":{"hundos":19,"performance":18,"accessibility":26,"cumulative":19},"lighthouse":{"version":"6.3.0","performance":0.73,"accessibility":0.93,"bestPractices":0.79,"seo":0.91,"total":336,"carbon":"0.148"},"firstContentfulPaint":1156.5500000000002,"speedIndex":3739.913955375662,"largestContentfulPaint":5705.662000000001,"totalBlockingTime":182.99999999999977,"cumulativeLayoutShift":0.051048834906684035,"timeToInteractive":4867.041,"maxPotentialFirstInputDelay":360.9999999999998,"timeToFirstByte":877.461,"weight":{"summary":"29 requests • 2,581 KiB","total":2642995,"image":1377592,"imageCount":12,"script":169582,"scriptCount":5,"document":17166,"font":324232,"fontCount":4,"stylesheet":31481,"stylesheetCount":1,"thirdParty":1152399,"thirdPartyCount":8},"axe":{"passes":626,"violations":33}},{"url":"https://www.aitoralcelay.eus/","requestedUrl":"https://www.aitoralcelay.eus/","timestamp":1598810609295,"ranks":{"hundos":20,"performance":29,"accessibility":31,"cumulative":20},"lighthouse":{"version":"6.3.0","performance":0.63,"accessibility":0.91,"bestPractices":0.86,"seo":0.96,"total":336,"carbon":"0.107"},"firstContentfulPaint":3100.9469999999997,"speedIndex":6102.79612275084,"largestContentfulPaint":4938.332,"totalBlockingTime":303.50000000000045,"cumulativeLayoutShift":0.0001611328125,"timeToInteractive":5018.832,"maxPotentialFirstInputDelay":291,"timeToFirstByte":1173.443,"weight":{"summary":"20 requests • 1,871 KiB","total":1915557,"image":1598510,"imageCount":11,"script":239295,"scriptCount":6,"document":8792,"font":20782,"fontCount":1,"stylesheet":48178,"stylesheetCount":1,"thirdParty":91674,"thirdPartyCount":5},"axe":{"passes":186,"violations":12}},{"url":"https://goongirl.org/","requestedUrl":"https://goongirl.org/","timestamp":1598812996285,"ranks":{"hundos":21,"performance":10,"accessibility":71,"cumulative":21},"lighthouse":{"version":"6.3.0","performance":0.87,"accessibility":0.83,"bestPractices":0.79,"seo":0.85,"total":334,"carbon":"0.0914"},"firstContentfulPaint":2686.653,"speedIndex":2894.656543065594,"largestContentfulPaint":2999.071,"totalBlockingTime":201,"cumulativeLayoutShift":0.2606576877170139,"timeToInteractive":3703.9069999999992,"maxPotentialFirstInputDelay":166,"timeToFirstByte":231.45099999999996,"weight":{"summary":"55 requests • 1,597 KiB","total":1635769,"image":1356417,"imageCount":25,"script":114049,"scriptCount":17,"document":6200,"font":76483,"fontCount":2,"stylesheet":82620,"stylesheetCount":10,"thirdParty":39584,"thirdPartyCount":9},"axe":{"passes":334,"violations":30}},{"url":"https://www.laurasteeples.uk/","requestedUrl":"https://www.laurasteeples.uk/","timestamp":1598812170241,"ranks":{"hundos":22,"performance":49,"accessibility":21,"cumulative":22},"lighthouse":{"version":"6.3.0","performance":0.46,"accessibility":0.94,"bestPractices":0.93,"seo":1,"total":333,"carbon":"0.0487"},"firstContentfulPaint":3271.236,"speedIndex":5615.15096371805,"largestContentfulPaint":6144.594,"totalBlockingTime":704.9599999999998,"cumulativeLayoutShift":0.16465026855468748,"timeToInteractive":5229.896000000001,"maxPotentialFirstInputDelay":772.9999999999998,"timeToFirstByte":93.37700000000001,"weight":{"summary":"31 requests • 851 KiB","total":871352,"image":444812,"imageCount":8,"script":216910,"scriptCount":13,"document":7277,"font":105214,"fontCount":3,"stylesheet":97139,"stylesheetCount":6,"thirdParty":85258,"thirdPartyCount":7},"axe":{"passes":223,"violations":18}},{"url":"https://www.conceptsecurite-formation.fr/","requestedUrl":"https://www.conceptsecurite-formation.fr/","timestamp":1598812345750,"ranks":{"hundos":23,"performance":6,"accessibility":66,"cumulative":23},"lighthouse":{"version":"6.3.0","performance":0.89,"accessibility":0.84,"bestPractices":0.71,"seo":0.86,"total":330,"carbon":"0.0202"},"firstContentfulPaint":1149.085,"speedIndex":2790.8526985608332,"largestContentfulPaint":1149.085,"totalBlockingTime":423,"cumulativeLayoutShift":0.08010009765625,"timeToInteractive":5055.776,"maxPotentialFirstInputDelay":302,"timeToFirstByte":302.37100000000004,"weight":{"summary":"17 requests • 353 KiB","total":361062,"image":13146,"imageCount":4,"script":337536,"scriptCount":7,"document":9659,"font":0,"fontCount":0,"stylesheet":0,"stylesheetCount":1,"thirdParty":112649,"thirdPartyCount":12},"axe":{"passes":215,"violations":16}},{"url":"https://www.shantom.gr/","requestedUrl":"https://www.shantom.gr/","timestamp":1598809878735,"ranks":{"hundos":24,"performance":38,"accessibility":17,"cumulative":24},"lighthouse":{"version":"6.3.0","performance":0.54,"accessibility":0.95,"bestPractices":0.79,"seo":0.99,"total":327,"carbon":"0.0983"},"firstContentfulPaint":2724.4440000000004,"speedIndex":5948.610625982938,"largestContentfulPaint":9129.151500000002,"totalBlockingTime":228.5,"cumulativeLayoutShift":0.0876054626463188,"timeToInteractive":8591.355500000001,"maxPotentialFirstInputDelay":192,"timeToFirstByte":631.003,"weight":{"summary":"89 requests • 1,717 KiB","total":1758694,"image":1124101,"imageCount":22,"script":226288,"scriptCount":12,"document":18579,"font":264342,"fontCount":12,"stylesheet":110471,"stylesheetCount":19,"thirdParty":200064,"thirdPartyCount":49},"axe":{"passes":707,"violations":30}},{"url":"https://www.florencepoiriernkpa.com/","requestedUrl":"https://www.florencepoiriernkpa.com/","timestamp":1598813172818,"ranks":{"hundos":25,"performance":16,"accessibility":96,"cumulative":25},"lighthouse":{"version":"6.3.0","performance":0.77,"accessibility":0.62,"bestPractices":0.93,"seo":0.92,"total":324,"carbon":"0.0843"},"firstContentfulPaint":3331.9060000000004,"speedIndex":4662.190853514446,"largestContentfulPaint":3455.1460000000006,"totalBlockingTime":285.7600000000002,"cumulativeLayoutShift":0.006966796875,"timeToInteractive":4687.546,"maxPotentialFirstInputDelay":373,"timeToFirstByte":310.86499999999995,"weight":{"summary":"57 requests • 1,474 KiB","total":1508903,"image":1063096,"imageCount":15,"script":254415,"scriptCount":18,"document":11475,"font":82883,"fontCount":3,"stylesheet":97034,"stylesheetCount":20,"thirdParty":55401,"thirdPartyCount":3},"axe":{"passes":450,"violations":34}},{"url":"https://www.hyundaiodn.co.za/","requestedUrl":"https://www.hyundaiodn.co.za/","timestamp":1598811692688,"ranks":{"hundos":26,"performance":2,"accessibility":43,"cumulative":26},"lighthouse":{"version":"6.3.0","performance":0.95,"accessibility":0.88,"bestPractices":0.86,"seo":0.55,"total":324,"carbon":"0.000828"},"firstContentfulPaint":2451.257,"speedIndex":2673.1448499998073,"largestContentfulPaint":2451.257,"totalBlockingTime":0,"cumulativeLayoutShift":0,"timeToInteractive":2451.257,"maxPotentialFirstInputDelay":16,"timeToFirstByte":250.68000000000006,"weight":{"summary":"2 requests • 14 KiB","total":14818,"image":0,"imageCount":0,"script":13771,"scriptCount":1,"document":1047,"font":0,"fontCount":0,"stylesheet":0,"stylesheetCount":0,"thirdParty":13771,"thirdPartyCount":1},"axe":{"passes":11,"violations":4}},{"url":"https://hondasc.co.za/","requestedUrl":"https://hondasc.co.za/","timestamp":1598812982525,"ranks":{"hundos":27,"performance":3,"accessibility":42,"cumulative":27},"lighthouse":{"version":"6.3.0","performance":0.95,"accessibility":0.88,"bestPractices":0.86,"seo":0.55,"total":324,"carbon":"0.000828"},"firstContentfulPaint":2456.558,"speedIndex":3038.349100000099,"largestContentfulPaint":2456.558,"totalBlockingTime":0,"cumulativeLayoutShift":0,"timeToInteractive":2456.558,"maxPotentialFirstInputDelay":16,"timeToFirstByte":263.0110000000001,"weight":{"summary":"2 requests • 14 KiB","total":14817,"image":0,"imageCount":0,"script":13772,"scriptCount":1,"document":1045,"font":0,"fontCount":0,"stylesheet":0,"stylesheetCount":0,"thirdParty":13772,"thirdPartyCount":1},"axe":{"passes":11,"violations":4}},{"url":"https://elchesemueve.com/","requestedUrl":"https://elchesemueve.com/","timestamp":1598811258077,"ranks":{"hundos":28,"performance":33,"accessibility":12,"cumulative":28},"lighthouse":{"version":"6.3.0","performance":0.57,"accessibility":0.96,"bestPractices":0.71,"seo":0.98,"total":322,"carbon":"0.101"},"firstContentfulPaint":2266.016,"speedIndex":6550.484445367562,"largestContentfulPaint":4219.331,"totalBlockingTime":597.0000000000005,"cumulativeLayoutShift":0.11245981852213542,"timeToInteractive":5902.586500000001,"maxPotentialFirstInputDelay":944.0000000000009,"timeToFirstByte":1960.96,"weight":{"summary":"56 requests • 1,764 KiB","total":1806645,"image":1147510,"imageCount":23,"script":168513,"scriptCount":18,"document":32683,"font":311966,"fontCount":6,"stylesheet":145973,"stylesheetCount":8,"thirdParty":66623,"thirdPartyCount":6},"axe":{"passes":1045,"violations":40}},{"url":"https://www.studiofive.ca/","requestedUrl":"https://www.studiofive.ca/","timestamp":1598810121853,"ranks":{"hundos":30,"performance":22,"accessibility":16,"cumulative":29},"lighthouse":{"version":"6.3.0","performance":0.69,"accessibility":0.95,"bestPractices":0.64,"seo":0.92,"total":320,"carbon":"0.129"},"firstContentfulPaint":2823.6549999999997,"speedIndex":25579.4991860441,"largestContentfulPaint":3189.3269999999998,"totalBlockingTime":91,"cumulativeLayoutShift":0.000447482638888889,"timeToInteractive":6824.539000000002,"maxPotentialFirstInputDelay":119,"timeToFirstByte":16406.337,"weight":{"summary":"69 requests • 2,257 KiB","total":2310758,"image":1342203,"imageCount":25,"script":147626,"scriptCount":27,"document":14142,"font":735517,"fontCount":5,"stylesheet":70843,"stylesheetCount":10,"thirdParty":19945,"thirdPartyCount":3},"axe":{"passes":874,"violations":29}},{"url":"https://www.santaremcultura.pt/","requestedUrl":"https://www.santaremcultura.pt/","timestamp":1598809908824,"ranks":{"hundos":29,"performance":30,"accessibility":33,"cumulative":30},"lighthouse":{"version":"6.3.0","performance":0.62,"accessibility":0.91,"bestPractices":0.71,"seo":0.96,"total":320,"carbon":"0.115"},"firstContentfulPaint":3061.752,"speedIndex":4488.747882489554,"largestContentfulPaint":5635.773999999999,"totalBlockingTime":172.5,"cumulativeLayoutShift":1.0668963623046874,"timeToInteractive":5441.771,"maxPotentialFirstInputDelay":157,"timeToFirstByte":462.2110000000001,"weight":{"summary":"57 requests • 2,016 KiB","total":2064250,"image":1528262,"imageCount":7,"script":304641,"scriptCount":20,"document":8758,"font":119373,"fontCount":5,"stylesheet":103216,"stylesheetCount":24,"thirdParty":256315,"thirdPartyCount":16},"axe":{"passes":536,"violations":39}},{"url":"https://e-liotrivi.gr/","requestedUrl":"https://e-liotrivi.gr/","timestamp":1598809592510,"ranks":{"hundos":31,"performance":23,"accessibility":67,"cumulative":31},"lighthouse":{"version":"6.3.0","performance":0.67,"accessibility":0.84,"bestPractices":0.79,"seo":0.89,"total":319,"carbon":"0.0880"},"firstContentfulPaint":3059.808,"speedIndex":4534.114152892478,"largestContentfulPaint":4411.753,"totalBlockingTime":355.1350000000002,"cumulativeLayoutShift":0.00036661783854166673,"timeToInteractive":6056.138000000001,"maxPotentialFirstInputDelay":273,"timeToFirstByte":247.50699999999995,"weight":{"summary":"49 requests • 1,539 KiB","total":1575574,"image":1036486,"imageCount":14,"script":292573,"scriptCount":21,"document":6332,"font":186926,"fontCount":2,"stylesheet":52814,"stylesheetCount":9,"thirdParty":242653,"thirdPartyCount":16},"axe":{"passes":425,"violations":27}},{"url":"https://www.asymptote.fr/fr.html","requestedUrl":"https://www.asymptote.fr/","timestamp":1598812356009,"ranks":{"hundos":32,"performance":26,"accessibility":57,"cumulative":32},"lighthouse":{"version":"6.3.0","performance":0.64,"accessibility":0.86,"bestPractices":0.79,"seo":0.89,"total":318,"carbon":"0.115"},"firstContentfulPaint":3174.2879999999996,"speedIndex":4101.391425904238,"largestContentfulPaint":7149.195,"totalBlockingTime":264.0000000000002,"cumulativeLayoutShift":0.14097015380859376,"timeToInteractive":4149.6735,"maxPotentialFirstInputDelay":205,"timeToFirstByte":183.78,"weight":{"summary":"60 requests • 2,004 KiB","total":2052551,"image":1658371,"imageCount":47,"script":268367,"scriptCount":8,"document":8159,"font":41188,"fontCount":2,"stylesheet":75873,"stylesheetCount":1,"thirdParty":59801,"thirdPartyCount":3},"axe":{"passes":686,"violations":29}},{"url":"https://kidstylesource.com/","requestedUrl":"http://kidstylesource.com/","timestamp":1598811745697,"ranks":{"hundos":33,"performance":24,"accessibility":35,"cumulative":33},"lighthouse":{"version":"6.3.0","performance":0.66,"accessibility":0.91,"bestPractices":0.71,"seo":0.88,"total":316,"carbon":"0.0633"},"firstContentfulPaint":3373.5099999999993,"speedIndex":4291.202988000317,"largestContentfulPaint":7310.009999999998,"totalBlockingTime":156.30000000000018,"cumulativeLayoutShift":0,"timeToInteractive":3625.0099999999993,"maxPotentialFirstInputDelay":260,"timeToFirstByte":576.452,"weight":{"summary":"35 requests • 1,106 KiB","total":1132579,"image":801338,"imageCount":9,"script":201039,"scriptCount":12,"document":5587,"font":47388,"fontCount":3,"stylesheet":76060,"stylesheetCount":8,"thirdParty":0,"thirdPartyCount":0},"axe":{"passes":288,"violations":43}},{"url":"https://www.rouchenergies.fr/","requestedUrl":"https://www.rouchenergies.fr/","timestamp":1598812614684,"ranks":{"hundos":34,"performance":27,"accessibility":50,"cumulative":34},"lighthouse":{"version":"6.3.0","performance":0.64,"accessibility":0.88,"bestPractices":0.86,"seo":0.77,"total":315,"carbon":"0.126"},"firstContentfulPaint":1583.1570000000002,"speedIndex":6107.709653806047,"largestContentfulPaint":1583.1570000000002,"totalBlockingTime":781,"cumulativeLayoutShift":0.05155347357855902,"timeToInteractive":9490.345499999998,"maxPotentialFirstInputDelay":726,"timeToFirstByte":1076.132,"weight":{"summary":"87 requests • 2,198 KiB","total":2250895,"image":1782132,"imageCount":71,"script":206012,"scriptCount":9,"document":25863,"font":146954,"fontCount":5,"stylesheet":89934,"stylesheetCount":1,"thirdParty":202159,"thirdPartyCount":7},"axe":{"passes":1034,"violations":54}},{"url":"https://www.solarpaneloptions.com.au/","requestedUrl":"https://www.solarpaneloptions.com.au/","timestamp":1598810717305,"ranks":{"hundos":35,"performance":39,"accessibility":59,"cumulative":35},"lighthouse":{"version":"6.3.0","performance":0.54,"accessibility":0.86,"bestPractices":0.79,"seo":0.96,"total":315,"carbon":"0.0844"},"firstContentfulPaint":4138.2699999999995,"speedIndex":6622.1988931995775,"largestContentfulPaint":6188.663999999999,"totalBlockingTime":32.5,"cumulativeLayoutShift":0.18555535210503474,"timeToInteractive":6017.0895,"maxPotentialFirstInputDelay":99,"timeToFirstByte":574.495,"weight":{"summary":"34 requests • 1,474 KiB","total":1509728,"image":1087178,"imageCount":8,"script":185796,"scriptCount":10,"document":5526,"font":121373,"fontCount":3,"stylesheet":106236,"stylesheetCount":8,"thirdParty":82891,"thirdPartyCount":7},"axe":{"passes":388,"violations":54}},{"url":"https://www.newprovidencelibrary.org/","requestedUrl":"https://www.newprovidencelibrary.org/","timestamp":1598810422618,"ranks":{"hundos":37,"performance":65,"accessibility":39,"cumulative":36},"lighthouse":{"version":"6.3.0","performance":0.38,"accessibility":0.9,"bestPractices":0.86,"seo":1,"total":314,"carbon":"0.0809"},"firstContentfulPaint":8769.341999999999,"speedIndex":8769.341999999999,"largestContentfulPaint":9715.034999999998,"totalBlockingTime":154.48499999999967,"cumulativeLayoutShift":0,"timeToInteractive":9350.997499999998,"maxPotentialFirstInputDelay":270,"timeToFirstByte":365.617,"weight":{"summary":"27 requests • 1,413 KiB","total":1447367,"image":134830,"imageCount":7,"script":625657,"scriptCount":9,"document":42260,"font":23735,"fontCount":2,"stylesheet":620885,"stylesheetCount":8,"thirdParty":19074,"thirdPartyCount":2},"axe":{"passes":306,"violations":37}},{"url":"https://www.garbald.ch/en/","requestedUrl":"https://www.garbald.ch/","timestamp":1598811816483,"ranks":{"hundos":36,"performance":45,"accessibility":41,"cumulative":37},"lighthouse":{"version":"6.3.0","performance":0.49,"accessibility":0.89,"bestPractices":0.93,"seo":0.83,"total":314,"carbon":"0.354"},"firstContentfulPaint":5370.7155,"speedIndex":6177.129393099875,"largestContentfulPaint":24148.775500000007,"totalBlockingTime":175.5,"cumulativeLayoutShift":0.014750108506944444,"timeToInteractive":5975.5035,"maxPotentialFirstInputDelay":162.5,"timeToFirstByte":179.526,"weight":{"summary":"54 requests • 6,194 KiB","total":6343064,"image":6045112,"imageCount":30,"script":106554,"scriptCount":12,"document":8866,"font":98009,"fontCount":2,"stylesheet":83923,"stylesheetCount":8,"thirdParty":27362,"thirdPartyCount":3},"axe":{"passes":629,"violations":65}},{"url":"https://www.tech-energy.gr/","requestedUrl":"https://www.tech-energy.gr/","timestamp":1598809919572,"ranks":{"hundos":38,"performance":44,"accessibility":34,"cumulative":38},"lighthouse":{"version":"6.3.0","performance":0.49,"accessibility":0.91,"bestPractices":0.79,"seo":0.95,"total":314,"carbon":"0.0511"},"firstContentfulPaint":3616.6550000000007,"speedIndex":5835.073021013989,"largestContentfulPaint":5935.3020000000015,"totalBlockingTime":520.6089999999995,"cumulativeLayoutShift":0.36084255642361107,"timeToInteractive":4262.046,"maxPotentialFirstInputDelay":385,"timeToFirstByte":931.9769999999999,"weight":{"summary":"50 requests • 893 KiB","total":914220,"image":576810,"imageCount":18,"script":238990,"scriptCount":20,"document":9737,"font":14079,"fontCount":2,"stylesheet":74604,"stylesheetCount":9,"thirdParty":66401,"thirdPartyCount":6},"axe":{"passes":500,"violations":40}},{"url":"https://www.121mathstuition.uk/","requestedUrl":"https://www.121mathstuition.uk/","timestamp":1598812233750,"ranks":{"hundos":40,"performance":75,"accessibility":38,"cumulative":39},"lighthouse":{"version":"6.3.0","performance":0.29,"accessibility":0.9,"bestPractices":0.93,"seo":1,"total":312,"carbon":"0.135"},"firstContentfulPaint":4640.940000000001,"speedIndex":7076.088865452557,"largestContentfulPaint":9234.057000000003,"totalBlockingTime":686,"cumulativeLayoutShift":0.26836903889973956,"timeToInteractive":8079.121500000001,"maxPotentialFirstInputDelay":1114,"timeToFirstByte":507.718,"weight":{"summary":"55 requests • 2,356 KiB","total":2412806,"image":1817025,"imageCount":18,"script":258688,"scriptCount":22,"document":9468,"font":181576,"fontCount":4,"stylesheet":146049,"stylesheetCount":10,"thirdParty":2403338,"thirdPartyCount":54},"axe":{"passes":413,"violations":30}},{"url":"https://www.vaagc.com/","requestedUrl":"https://www.vaagc.com/","timestamp":1598810140838,"ranks":{"hundos":39,"performance":50,"accessibility":18,"cumulative":40},"lighthouse":{"version":"6.3.0","performance":0.46,"accessibility":0.95,"bestPractices":0.79,"seo":0.92,"total":312,"carbon":"0.135"},"firstContentfulPaint":3426.7990000000004,"speedIndex":6163.21847911544,"largestContentfulPaint":5093.983000000002,"totalBlockingTime":618.4279999999999,"cumulativeLayoutShift":0.3949623548719618,"timeToInteractive":5651.5205000000005,"maxPotentialFirstInputDelay":471,"timeToFirstByte":719.356,"weight":{"summary":"57 requests • 2,355 KiB","total":2411353,"image":1959872,"imageCount":14,"script":201720,"scriptCount":15,"document":12313,"font":125259,"fontCount":5,"stylesheet":111918,"stylesheetCount":21,"thirdParty":107628,"thirdPartyCount":11},"axe":{"passes":1086,"violations":32}},{"url":"https://gene-watson.com/","requestedUrl":"https://gene-watson.com/","timestamp":1598812242381,"ranks":{"hundos":41,"performance":25,"accessibility":82,"cumulative":41},"lighthouse":{"version":"6.3.0","performance":0.64,"accessibility":0.77,"bestPractices":0.71,"seo":0.99,"total":311,"carbon":"0.101"},"firstContentfulPaint":3556.541,"speedIndex":4027.631888382318,"largestContentfulPaint":5692.891500000001,"totalBlockingTime":181.5,"cumulativeLayoutShift":0.17872585720486112,"timeToInteractive":5692.891500000001,"maxPotentialFirstInputDelay":279,"timeToFirstByte":323.15,"weight":{"summary":"71 requests • 1,766 KiB","total":1808601,"image":1289904,"imageCount":29,"script":221667,"scriptCount":14,"document":13775,"font":159651,"fontCount":5,"stylesheet":123604,"stylesheetCount":21,"thirdParty":237264,"thirdPartyCount":12},"axe":{"passes":804,"violations":34}},{"url":"https://www.rcsmn.fr/","requestedUrl":"https://www.rcsmn.fr/","timestamp":1598811884026,"ranks":{"hundos":42,"performance":64,"accessibility":19,"cumulative":42},"lighthouse":{"version":"6.3.0","performance":0.38,"accessibility":0.95,"bestPractices":0.86,"seo":0.92,"total":311,"carbon":"0.132"},"firstContentfulPaint":3386.9290000000005,"speedIndex":7852.124893878099,"largestContentfulPaint":9413.505500000003,"totalBlockingTime":376,"cumulativeLayoutShift":0.2584723917643229,"timeToInteractive":12701.257000000001,"maxPotentialFirstInputDelay":250,"timeToFirstByte":511.08199999999994,"weight":{"summary":"75 requests • 2,309 KiB","total":2364309,"image":1130918,"imageCount":12,"script":760230,"scriptCount":26,"document":29756,"font":274027,"fontCount":10,"stylesheet":168552,"stylesheetCount":24,"thirdParty":919060,"thirdPartyCount":20},"axe":{"passes":1365,"violations":50}},{"url":"https://aslterresbasses.org/","requestedUrl":"https://aslterresbasses.org/","timestamp":1598812338619,"ranks":{"hundos":43,"performance":36,"accessibility":68,"cumulative":43},"lighthouse":{"version":"6.3.0","performance":0.55,"accessibility":0.84,"bestPractices":0.79,"seo":0.92,"total":310,"carbon":"0.247"},"firstContentfulPaint":2715.4089999999997,"speedIndex":5320.503183141084,"largestContentfulPaint":9308.966999999999,"totalBlockingTime":153,"cumulativeLayoutShift":0.2753860812717014,"timeToInteractive":7486.135,"maxPotentialFirstInputDelay":156,"timeToFirstByte":272.02500000000003,"weight":{"summary":"56 requests • 4,325 KiB","total":4428918,"image":4147270,"imageCount":19,"script":98410,"scriptCount":17,"document":12351,"font":108414,"fontCount":3,"stylesheet":62473,"stylesheetCount":16,"thirdParty":32388,"thirdPartyCount":3},"axe":{"passes":633,"violations":32}},{"url":"https://www.absolutemusictrust.org/","requestedUrl":"https://www.absolutemusictrust.org/","timestamp":1598811662961,"ranks":{"hundos":44,"performance":47,"accessibility":62,"cumulative":44},"lighthouse":{"version":"6.3.0","performance":0.47,"accessibility":0.85,"bestPractices":0.86,"seo":0.92,"total":310,"carbon":"1.34"},"firstContentfulPaint":2191.5730000000003,"speedIndex":6372.24809081748,"largestContentfulPaint":5539.316500000001,"totalBlockingTime":477.5,"cumulativeLayoutShift":0.30943901231553816,"timeToInteractive":9867.979000000001,"maxPotentialFirstInputDelay":345,"timeToFirstByte":1480.599,"weight":{"summary":"54 requests • 23,339 KiB","total":23899538,"image":22814080,"imageCount":10,"script":630060,"scriptCount":18,"document":33121,"font":258630,"fontCount":7,"stylesheet":161381,"stylesheetCount":15,"thirdParty":842921,"thirdPartyCount":21},"axe":{"passes":551,"violations":31}},{"url":"https://dbtitlellc.com/","requestedUrl":"https://dbtitlellc.com/","timestamp":1598811358745,"ranks":{"hundos":45,"performance":83,"accessibility":1,"cumulative":45},"lighthouse":{"version":"6.3.0","performance":0.23,"accessibility":1,"bestPractices":0.86,"seo":1,"total":309,"carbon":"0.122"},"firstContentfulPaint":9678.071999999998,"speedIndex":9678.071999999998,"largestContentfulPaint":13952.725,"totalBlockingTime":539,"cumulativeLayoutShift":0.018253173828125,"timeToInteractive":14473.020999999997,"maxPotentialFirstInputDelay":268.5,"timeToFirstByte":499.514,"weight":{"summary":"44 requests • 2,124 KiB","total":2174837,"image":190991,"imageCount":5,"script":819309,"scriptCount":18,"document":23226,"font":81217,"fontCount":5,"stylesheet":1059191,"stylesheetCount":10,"thirdParty":250490,"thirdPartyCount":17},"axe":{"passes":263,"violations":7}},{"url":"https://stormbay.com.au/","requestedUrl":"https://stormbay.com.au/","timestamp":1598812575323,"ranks":{"hundos":46,"performance":59,"accessibility":10,"cumulative":46},"lighthouse":{"version":"6.3.0","performance":0.42,"accessibility":0.96,"bestPractices":0.71,"seo":1,"total":309,"carbon":"0.0669"},"firstContentfulPaint":3632.301,"speedIndex":6599.879061874746,"largestContentfulPaint":9549.473999999998,"totalBlockingTime":367.5,"cumulativeLayoutShift":0.23273602973090277,"timeToInteractive":9290.810000000001,"maxPotentialFirstInputDelay":196,"timeToFirstByte":912.1689999999999,"weight":{"summary":"71 requests • 1,170 KiB","total":1197643,"image":357223,"imageCount":17,"script":574945,"scriptCount":28,"document":15936,"font":187727,"fontCount":5,"stylesheet":55482,"stylesheetCount":12,"thirdParty":587507,"thirdPartyCount":35},"axe":{"passes":456,"violations":20}},{"url":"https://uplewiscounty.org/","requestedUrl":"https://uplewiscounty.org/","timestamp":1598813153557,"ranks":{"hundos":47,"performance":70,"accessibility":20,"cumulative":47},"lighthouse":{"version":"6.3.0","performance":0.35,"accessibility":0.94,"bestPractices":0.79,"seo":1,"total":308,"carbon":"0.429"},"firstContentfulPaint":9156.942,"speedIndex":9156.942,"largestContentfulPaint":11868.21,"totalBlockingTime":152.5,"cumulativeLayoutShift":0.05789997016059028,"timeToInteractive":11907.103500000001,"maxPotentialFirstInputDelay":253,"timeToFirstByte":459.536,"weight":{"summary":"33 requests • 7,497 KiB","total":7676975,"image":13818,"imageCount":3,"script":1091894,"scriptCount":13,"document":9913,"font":93954,"fontCount":5,"stylesheet":532296,"stylesheetCount":5,"thirdParty":55390,"thirdPartyCount":3},"axe":{"passes":173,"violations":6}},{"url":"https://gbaprojects.com.au/","requestedUrl":"https://gbaprojects.com.au/","timestamp":1598811551410,"ranks":{"hundos":48,"performance":34,"accessibility":69,"cumulative":48},"lighthouse":{"version":"6.3.0","performance":0.57,"accessibility":0.84,"bestPractices":0.79,"seo":0.88,"total":308,"carbon":"0.104"},"firstContentfulPaint":3155.597999999999,"speedIndex":8330.743801238325,"largestContentfulPaint":8547.029499999997,"totalBlockingTime":1.5,"cumulativeLayoutShift":0.02069091796875,"timeToInteractive":3847.7929999999988,"maxPotentialFirstInputDelay":53,"timeToFirstByte":663.9060000000001,"weight":{"summary":"30 requests • 1,811 KiB","total":1854626,"image":1600213,"imageCount":10,"script":113967,"scriptCount":7,"document":4661,"font":115560,"fontCount":4,"stylesheet":18471,"stylesheetCount":5,"thirdParty":92189,"thirdPartyCount":6},"axe":{"passes":438,"violations":49}},{"url":"https://www.henniker-plasma.nl/","requestedUrl":"https://www.henniker-plasma.nl/","timestamp":1598810832057,"ranks":{"hundos":49,"performance":74,"accessibility":13,"cumulative":49},"lighthouse":{"version":"6.3.0","performance":0.32,"accessibility":0.96,"bestPractices":0.86,"seo":0.91,"total":305,"carbon":"0.214"},"firstContentfulPaint":3122.5130000000004,"speedIndex":8464.815978127215,"largestContentfulPaint":5677.8655,"totalBlockingTime":1074.5,"cumulativeLayoutShift":0.14045665825737846,"timeToInteractive":8430.9835,"maxPotentialFirstInputDelay":1535,"timeToFirstByte":1137.813,"weight":{"summary":"138 requests • 3,732 KiB","total":3821102,"image":3226822,"imageCount":98,"script":279621,"scriptCount":19,"document":18957,"font":153087,"fontCount":5,"stylesheet":141924,"stylesheetCount":11,"thirdParty":2143967,"thirdPartyCount":46},"axe":{"passes":719,"violations":49}},{"url":"https://karangploso.jatim.bmkg.go.id/","requestedUrl":"https://karangploso.jatim.bmkg.go.id/","timestamp":1598809800940,"ranks":{"hundos":51,"performance":55,"accessibility":27,"cumulative":50},"lighthouse":{"version":"6.3.0","performance":0.43,"accessibility":0.93,"bestPractices":0.71,"seo":0.97,"total":304,"carbon":"0.0316"},"firstContentfulPaint":1939.7399999999998,"speedIndex":7852.305869831224,"largestContentfulPaint":2014.2399999999998,"totalBlockingTime":38115.315,"cumulativeLayoutShift":0.7152590467664931,"timeToInteractive":51130.850000000006,"maxPotentialFirstInputDelay":2551,"timeToFirstByte":1257.035,"weight":{"summary":"32 requests • 551 KiB","total":564686,"image":189096,"imageCount":18,"script":278009,"scriptCount":9,"document":19931,"font":33695,"fontCount":1,"stylesheet":43244,"stylesheetCount":1,"thirdParty":51879,"thirdPartyCount":20},"axe":{"error":{"name":"TimeoutError"}}},{"url":"https://www.vinodocekal.cz/","requestedUrl":"https://www.vinodocekal.cz/","timestamp":1598811340611,"ranks":{"hundos":50,"performance":77,"accessibility":9,"cumulative":51},"lighthouse":{"version":"6.3.0","performance":0.29,"accessibility":0.96,"bestPractices":0.79,"seo":1,"total":304,"carbon":"0.185"},"firstContentfulPaint":9423.1695,"speedIndex":40757.85989383816,"largestContentfulPaint":12660.221999999998,"totalBlockingTime":16.5,"cumulativeLayoutShift":0.40886686197916666,"timeToInteractive":12423.558,"maxPotentialFirstInputDelay":42,"timeToFirstByte":20272.825,"weight":{"summary":"45 requests • 3,235 KiB","total":3312891,"image":2032207,"imageCount":6,"script":397832,"scriptCount":14,"document":6127,"font":287529,"fontCount":5,"stylesheet":589196,"stylesheetCount":19,"thirdParty":2976,"thirdPartyCount":2},"axe":{"passes":277,"violations":11}},{"url":"https://www.brillianttours.com/","requestedUrl":"https://www.brillianttours.com/","timestamp":1598810913262,"ranks":{"hundos":52,"performance":68,"accessibility":32,"cumulative":52},"lighthouse":{"version":"6.3.0","performance":0.35,"accessibility":0.91,"bestPractices":0.93,"seo":0.84,"total":303,"carbon":"0.275"},"firstContentfulPaint":4101.84,"speedIndex":6365.757360925111,"largestContentfulPaint":13182.9915,"totalBlockingTime":754.4999999999991,"cumulativeLayoutShift":0.1823209635416667,"timeToInteractive":6004.412499999999,"maxPotentialFirstInputDelay":1243,"timeToFirstByte":417.53799999999995,"weight":{"summary":"63 requests • 4,808 KiB","total":4923330,"image":4457492,"imageCount":36,"script":191746,"scriptCount":11,"document":13470,"font":118986,"fontCount":5,"stylesheet":140990,"stylesheetCount":9,"thirdParty":4903312,"thirdPartyCount":58},"axe":{"passes":496,"violations":37}},{"url":"https://www.cardecsxm.com/","requestedUrl":"https://www.cardecsxm.com/","timestamp":1598810551148,"ranks":{"hundos":53,"performance":71,"accessibility":40,"cumulative":53},"lighthouse":{"version":"6.3.0","performance":0.34,"accessibility":0.9,"bestPractices":0.79,"seo":0.98,"total":301,"carbon":"0.0639"},"firstContentfulPaint":3944.3860000000004,"speedIndex":6306.036117911717,"largestContentfulPaint":6508.967000000001,"totalBlockingTime":982.5,"cumulativeLayoutShift":0.15301200358072917,"timeToInteractive":6439.577000000001,"maxPotentialFirstInputDelay":305,"timeToFirstByte":857.04,"weight":{"summary":"80 requests • 1,117 KiB","total":1143910,"image":618651,"imageCount":22,"script":363517,"scriptCount":22,"document":31233,"font":48263,"fontCount":6,"stylesheet":81951,"stylesheetCount":26,"thirdParty":234225,"thirdPartyCount":18},"axe":{"passes":641,"violations":63}},{"url":"https://www.muoversiliberi.it/","requestedUrl":"https://www.muoversiliberi.it/","timestamp":1598811840505,"ranks":{"hundos":55,"performance":58,"accessibility":52,"cumulative":54},"lighthouse":{"version":"6.3.0","performance":0.42,"accessibility":0.88,"bestPractices":0.71,"seo":0.99,"total":300,"carbon":"0.0850"},"firstContentfulPaint":1972.253,"speedIndex":4938.376555811352,"largestContentfulPaint":10955.827999999998,"totalBlockingTime":640.876,"cumulativeLayoutShift":0.8059272596571181,"timeToInteractive":8312.1105,"maxPotentialFirstInputDelay":416,"timeToFirstByte":354.6089999999999,"weight":{"summary":"29 requests • 1,486 KiB","total":1521742,"image":548553,"imageCount":7,"script":468017,"scriptCount":7,"document":16212,"font":422406,"fontCount":11,"stylesheet":66554,"stylesheetCount":3,"thirdParty":466173,"thirdPartyCount":17},"axe":{"passes":1240,"violations":86}},{"url":"https://gypsosanideskiriakidis.gr/","requestedUrl":"https://gypsosanideskiriakidis.gr/","timestamp":1598811945591,"ranks":{"hundos":54,"performance":37,"accessibility":53,"cumulative":55},"lighthouse":{"version":"6.3.0","performance":0.55,"accessibility":0.87,"bestPractices":0.64,"seo":0.91,"total":300,"carbon":"0.0714"},"firstContentfulPaint":3760.6949999999997,"speedIndex":5671.8616173253395,"largestContentfulPaint":7932.492999999999,"totalBlockingTime":200.5,"cumulativeLayoutShift":0.10253896077473956,"timeToInteractive":6226.660499999999,"maxPotentialFirstInputDelay":221,"timeToFirstByte":455.118,"weight":{"summary":"46 requests • 1,249 KiB","total":1278514,"image":729720,"imageCount":10,"script":337844,"scriptCount":19,"document":36546,"font":72163,"fontCount":1,"stylesheet":99606,"stylesheetCount":12,"thirdParty":283578,"thirdPartyCount":14},"axe":{"passes":376,"violations":9}},{"url":"https://www.shelterforhelpinemergency.org/","requestedUrl":"https://www.shelterforhelpinemergency.org/","timestamp":1598810161154,"ranks":{"hundos":56,"performance":52,"accessibility":49,"cumulative":56},"lighthouse":{"version":"6.3.0","performance":0.45,"accessibility":0.88,"bestPractices":0.71,"seo":0.91,"total":295,"carbon":"0.0822"},"firstContentfulPaint":3752.7940000000003,"speedIndex":5216.26654436026,"largestContentfulPaint":7421.0470000000005,"totalBlockingTime":646.3035,"cumulativeLayoutShift":0.061007941351996525,"timeToInteractive":5915.617,"maxPotentialFirstInputDelay":471,"timeToFirstByte":430.99800000000005,"weight":{"summary":"64 requests • 1,436 KiB","total":1470959,"image":761589,"imageCount":14,"script":219296,"scriptCount":18,"document":59090,"font":287156,"fontCount":9,"stylesheet":143828,"stylesheetCount":22,"thirdParty":140970,"thirdPartyCount":12},"axe":{"passes":651,"violations":44}},{"url":"https://cuisinetrail.com/","requestedUrl":"https://cuisinetrail.com/","timestamp":1598812659776,"ranks":{"hundos":59,"performance":73,"accessibility":25,"cumulative":57},"lighthouse":{"version":"6.3.0","performance":0.32,"accessibility":0.93,"bestPractices":0.79,"seo":0.9,"total":294,"carbon":"0.0792"},"firstContentfulPaint":5917.847999999999,"speedIndex":7530.844331525745,"largestContentfulPaint":7847.049499999999,"totalBlockingTime":443.98800000000074,"cumulativeLayoutShift":0.22430725097656248,"timeToInteractive":10028.7055,"maxPotentialFirstInputDelay":207,"timeToFirstByte":863.746,"weight":{"summary":"59 requests • 1,384 KiB","total":1417005,"image":281746,"imageCount":20,"script":653840,"scriptCount":25,"document":14601,"font":63744,"fontCount":4,"stylesheet":402945,"stylesheetCount":8,"thirdParty":421969,"thirdPartyCount":33},"axe":{"passes":712,"violations":18}},{"url":"https://www.aldersportswear.com/","requestedUrl":"https://www.aldersportswear.com/","timestamp":1598810871015,"ranks":{"hundos":57,"performance":51,"accessibility":75,"cumulative":58},"lighthouse":{"version":"6.3.0","performance":0.46,"accessibility":0.81,"bestPractices":0.86,"seo":0.81,"total":294,"carbon":"0.226"},"firstContentfulPaint":4735.719999999999,"speedIndex":7403.3858587347,"largestContentfulPaint":5371.592000000001,"totalBlockingTime":177,"cumulativeLayoutShift":0.18350868055555555,"timeToInteractive":10187.724,"maxPotentialFirstInputDelay":353,"timeToFirstByte":372.245,"weight":{"summary":"38 requests • 3,952 KiB","total":4046541,"image":3254729,"imageCount":13,"script":290965,"scriptCount":13,"document":35179,"font":111156,"fontCount":2,"stylesheet":354512,"stylesheetCount":9,"thirdParty":90497,"thirdPartyCount":6},"axe":{"passes":468,"violations":25}},{"url":"https://www.smhampton.catholic.edu.au/","requestedUrl":"https://www.smhampton.catholic.edu.au/","timestamp":1598809425721,"ranks":{"hundos":58,"performance":42,"accessibility":84,"cumulative":59},"lighthouse":{"version":"6.3.0","performance":0.51,"accessibility":0.76,"bestPractices":0.79,"seo":0.88,"total":294,"carbon":"0.0750"},"firstContentfulPaint":3504.725,"speedIndex":6445.2422704248065,"largestContentfulPaint":6836.2145,"totalBlockingTime":138.00000000000023,"cumulativeLayoutShift":0.23040804036458332,"timeToInteractive":7943.211000000001,"maxPotentialFirstInputDelay":158,"timeToFirstByte":373.56399999999996,"weight":{"summary":"43 requests • 1,311 KiB","total":1342531,"image":848318,"imageCount":12,"script":307185,"scriptCount":17,"document":7817,"font":159461,"fontCount":4,"stylesheet":17994,"stylesheetCount":5,"thirdParty":332410,"thirdPartyCount":21},"axe":{"passes":646,"violations":39}},{"url":"https://www.vsesv.com/","requestedUrl":"https://www.vsesv.com/","timestamp":1598810880142,"ranks":{"hundos":60,"performance":57,"accessibility":55,"cumulative":60},"lighthouse":{"version":"6.3.0","performance":0.43,"accessibility":0.87,"bestPractices":0.79,"seo":0.84,"total":293,"carbon":"0.105"},"firstContentfulPaint":4075.3520000000003,"speedIndex":11493.529879090582,"largestContentfulPaint":7423.108000000002,"totalBlockingTime":30.5,"cumulativeLayoutShift":0.00032432725694444447,"timeToInteractive":10602.710000000003,"maxPotentialFirstInputDelay":64.5,"timeToFirstByte":519.1690000000001,"weight":{"summary":"44 requests • 1,842 KiB","total":1885720,"image":1633490,"imageCount":20,"script":175396,"scriptCount":13,"document":7015,"font":9522,"fontCount":1,"stylesheet":60297,"stylesheetCount":9,"thirdParty":65949,"thirdPartyCount":5},"axe":{"passes":179,"violations":37}},{"url":"https://www.blinser.cl/","requestedUrl":"https://www.blinser.cl/","timestamp":1598810758678,"ranks":{"hundos":61,"performance":41,"accessibility":90,"cumulative":61},"lighthouse":{"version":"6.3.0","performance":0.53,"accessibility":0.72,"bestPractices":0.86,"seo":0.82,"total":293,"carbon":"0.0696"},"firstContentfulPaint":4940.0655,"speedIndex":8028.141965999939,"largestContentfulPaint":5130.716,"totalBlockingTime":137,"cumulativeLayoutShift":0.17591752115885417,"timeToInteractive":5650.001,"maxPotentialFirstInputDelay":92,"timeToFirstByte":1896.122,"weight":{"summary":"54 requests • 1,217 KiB","total":1245811,"image":862990,"imageCount":22,"script":213960,"scriptCount":17,"document":9718,"font":105902,"fontCount":2,"stylesheet":52464,"stylesheetCount":10,"thirdParty":94805,"thirdPartyCount":8},"axe":{"passes":656,"violations":42}},{"url":"https://steelemotors.com/","requestedUrl":"https://steelemotors.com/","timestamp":1598811908553,"ranks":{"hundos":62,"performance":84,"accessibility":44,"cumulative":62},"lighthouse":{"version":"6.3.0","performance":0.18,"accessibility":0.88,"bestPractices":0.86,"seo":1,"total":292,"carbon":"0.244"},"firstContentfulPaint":7005.685000000001,"speedIndex":7272.682991090331,"largestContentfulPaint":14568.831,"totalBlockingTime":877,"cumulativeLayoutShift":0.021495015462239583,"timeToInteractive":16559.191401855467,"maxPotentialFirstInputDelay":344,"timeToFirstByte":431.333,"weight":{"summary":"43 requests • 4,256 KiB","total":4357862,"image":2854986,"imageCount":10,"script":737357,"scriptCount":18,"document":18342,"font":84403,"fontCount":5,"stylesheet":656426,"stylesheetCount":6,"thirdParty":264313,"thirdPartyCount":14},"axe":{"passes":221,"violations":12}},{"url":"https://www.mac-isa.org/","requestedUrl":"https://www.mac-isa.org/","timestamp":1598810172908,"ranks":{"hundos":64,"performance":43,"accessibility":58,"cumulative":63},"lighthouse":{"version":"6.3.0","performance":0.5,"accessibility":0.86,"bestPractices":0.64,"seo":0.92,"total":292,"carbon":"0.0765"},"firstContentfulPaint":2575.758,"speedIndex":7436.612846633727,"largestContentfulPaint":3940.91,"totalBlockingTime":1049.7640000000006,"cumulativeLayoutShift":0.004499823676215277,"timeToInteractive":5612.935,"maxPotentialFirstInputDelay":609,"timeToFirstByte":1100.75,"weight":{"summary":"48 requests • 1,337 KiB","total":1369489,"image":664334,"imageCount":16,"script":247916,"scriptCount":11,"document":13816,"font":216791,"fontCount":2,"stylesheet":126288,"stylesheetCount":5,"thirdParty":19074,"thirdPartyCount":5},"axe":{"passes":1095,"violations":31}},{"url":"https://donation.reservenaturelle-saint-martin.com/","requestedUrl":"https://donation.reservenaturelle-saint-martin.com/","timestamp":1598811022229,"ranks":{"hundos":63,"performance":40,"accessibility":83,"cumulative":64},"lighthouse":{"version":"6.3.0","performance":0.53,"accessibility":0.77,"bestPractices":0.79,"seo":0.83,"total":292,"carbon":"0.114"},"firstContentfulPaint":4234.544,"speedIndex":5702.515736277441,"largestContentfulPaint":10275.300000000001,"totalBlockingTime":136.3119999999999,"cumulativeLayoutShift":0.4532701416015625,"timeToInteractive":4780.208,"maxPotentialFirstInputDelay":185,"timeToFirstByte":501.129,"weight":{"summary":"50 requests • 1,999 KiB","total":2047384,"image":1714346,"imageCount":14,"script":103781,"scriptCount":16,"document":12572,"font":141598,"fontCount":4,"stylesheet":75087,"stylesheetCount":15,"thirdParty":79941,"thirdPartyCount":8},"axe":{"passes":622,"violations":44}},{"url":"https://www.terra-relaxa.gr/","requestedUrl":"https://www.terra-relaxa.gr/","timestamp":1598812810711,"ranks":{"hundos":65,"performance":35,"accessibility":87,"cumulative":65},"lighthouse":{"version":"6.3.0","performance":0.55,"accessibility":0.75,"bestPractices":0.71,"seo":0.9,"total":291,"carbon":"0.126"},"firstContentfulPaint":4592.562000000001,"speedIndex":5211.897064196012,"largestContentfulPaint":7374.774,"totalBlockingTime":59,"cumulativeLayoutShift":0.007363016764322917,"timeToInteractive":6112.668,"maxPotentialFirstInputDelay":129,"timeToFirstByte":238.96300000000002,"weight":{"summary":"54 requests • 2,199 KiB","total":2251656,"image":1537111,"imageCount":26,"script":302177,"scriptCount":12,"document":8802,"font":101958,"fontCount":3,"stylesheet":300831,"stylesheetCount":10,"thirdParty":81724,"thirdPartyCount":8},"axe":{"passes":369,"violations":33}},{"url":"https://www.cspt-training.co.uk/","requestedUrl":"https://www.cspt-training.co.uk/","timestamp":1598810890390,"ranks":{"hundos":66,"performance":81,"accessibility":28,"cumulative":66},"lighthouse":{"version":"6.3.0","performance":0.25,"accessibility":0.92,"bestPractices":0.93,"seo":0.81,"total":291,"carbon":"0.102"},"firstContentfulPaint":4442.109,"speedIndex":6882.504527212123,"largestContentfulPaint":7664.991499999998,"totalBlockingTime":1626.7175000000002,"cumulativeLayoutShift":0.16580246946857205,"timeToInteractive":6691.8189999999995,"maxPotentialFirstInputDelay":1663,"timeToFirstByte":348.27400000000006,"weight":{"summary":"54 requests • 1,779 KiB","total":1822109,"image":1286452,"imageCount":19,"script":206310,"scriptCount":16,"document":11774,"font":166008,"fontCount":4,"stylesheet":151565,"stylesheetCount":14,"thirdParty":1810335,"thirdPartyCount":53},"axe":{"passes":390,"violations":33}},{"url":"https://bobsgotskills.com/","requestedUrl":"https://bobsgotskills.com/","timestamp":1598811533644,"ranks":{"hundos":68,"performance":46,"accessibility":78,"cumulative":67},"lighthouse":{"version":"6.3.0","performance":0.49,"accessibility":0.8,"bestPractices":0.79,"seo":0.83,"total":291,"carbon":"0.0621"},"firstContentfulPaint":4473.58,"speedIndex":6742.687820546572,"largestContentfulPaint":6267.799999999999,"totalBlockingTime":248.5,"cumulativeLayoutShift":0.27320855034722225,"timeToInteractive":6108.1669999999995,"maxPotentialFirstInputDelay":250,"timeToFirstByte":1100.18,"weight":{"summary":"91 requests • 1,086 KiB","total":1111569,"image":482679,"imageCount":26,"script":265182,"scriptCount":29,"document":23136,"font":262369,"fontCount":5,"stylesheet":78094,"stylesheetCount":29,"thirdParty":84085,"thirdPartyCount":9},"axe":{"passes":1057,"violations":56}},{"url":"https://capitalcarhire.co.za/","requestedUrl":"https://www.capitalcarhire.co.za/","timestamp":1598810988052,"ranks":{"hundos":67,"performance":80,"accessibility":81,"cumulative":68},"lighthouse":{"version":"6.3.0","performance":0.27,"accessibility":0.78,"bestPractices":0.93,"seo":0.93,"total":291,"carbon":"0.198"},"firstContentfulPaint":5927.685,"speedIndex":16057.924548344143,"largestContentfulPaint":12969.685000000001,"totalBlockingTime":441.5,"cumulativeLayoutShift":0.00911568874782986,"timeToInteractive":13022.185000000001,"maxPotentialFirstInputDelay":561,"timeToFirstByte":1094.503,"weight":{"summary":"132 requests • 3,454 KiB","total":3536610,"image":2430674,"imageCount":18,"script":469026,"scriptCount":60,"document":24929,"font":350535,"fontCount":12,"stylesheet":259383,"stylesheetCount":36,"thirdParty":154903,"thirdPartyCount":16},"axe":{"passes":1056,"violations":141}},{"url":"https://alter-it.com.au/","requestedUrl":"https://alter-it.com.au/","timestamp":1598812057327,"ranks":{"hundos":70,"performance":54,"accessibility":93,"cumulative":69},"lighthouse":{"version":"6.3.0","performance":0.44,"accessibility":0.7,"bestPractices":0.79,"seo":0.97,"total":290,"carbon":"0.103"},"firstContentfulPaint":3979.768,"speedIndex":8190.092899776675,"largestContentfulPaint":11389.513999999997,"totalBlockingTime":192.5,"cumulativeLayoutShift":0.009368713378906249,"timeToInteractive":10710.929999999998,"maxPotentialFirstInputDelay":124,"timeToFirstByte":906.795,"weight":{"summary":"59 requests • 1,807 KiB","total":1850752,"image":1122955,"imageCount":22,"script":574226,"scriptCount":19,"document":9826,"font":119971,"fontCount":3,"stylesheet":20919,"stylesheetCount":6,"thirdParty":549178,"thirdPartyCount":24},"axe":{"passes":671,"violations":55}},{"url":"https://www.orrido-cavaglia.ch/it/","requestedUrl":"http://www.orrido-cavaglia.ch/","timestamp":1598813083288,"ranks":{"hundos":71,"performance":56,"accessibility":63,"cumulative":70},"lighthouse":{"version":"6.3.0","performance":0.43,"accessibility":0.85,"bestPractices":0.79,"seo":0.82,"total":289,"carbon":"0.205"},"firstContentfulPaint":5850.622499999998,"speedIndex":7856.9242450676265,"largestContentfulPaint":9301.636999999999,"totalBlockingTime":251.5,"cumulativeLayoutShift":0.0021131727430555554,"timeToInteractive":6830.774999999999,"maxPotentialFirstInputDelay":226,"timeToFirstByte":206.331,"weight":{"summary":"44 requests • 3,585 KiB","total":3671236,"image":2886271,"imageCount":16,"script":106195,"scriptCount":12,"document":11659,"font":109435,"fontCount":4,"stylesheet":80874,"stylesheetCount":8,"thirdParty":38708,"thirdPartyCount":5},"axe":{"passes":587,"violations":51}},{"url":"https://www.verdesxm.com/","requestedUrl":"https://www.verdesxm.com/","timestamp":1598809697338,"ranks":{"hundos":72,"performance":82,"accessibility":60,"cumulative":71},"lighthouse":{"version":"6.3.0","performance":0.24,"accessibility":0.86,"bestPractices":0.93,"seo":0.83,"total":286,"carbon":"0.102"},"firstContentfulPaint":4049.1,"speedIndex":7231.493948731948,"largestContentfulPaint":7854.083999999999,"totalBlockingTime":1366.5,"cumulativeLayoutShift":0.02376626247829861,"timeToInteractive":9553.036999999998,"maxPotentialFirstInputDelay":482,"timeToFirstByte":303.27600000000007,"weight":{"summary":"103 requests • 1,779 KiB","total":1821321,"image":941600,"imageCount":29,"script":569607,"scriptCount":32,"document":24493,"font":189509,"fontCount":11,"stylesheet":95872,"stylesheetCount":27,"thirdParty":704821,"thirdPartyCount":50},"axe":{"passes":992,"violations":61}},{"url":"https://www.volharding-hout-blerick.nl/","requestedUrl":"http://volharding-hout-blerick.nl/","timestamp":1598811681505,"ranks":{"hundos":73,"performance":69,"accessibility":45,"cumulative":72},"lighthouse":{"version":"6.3.0","performance":0.35,"accessibility":0.88,"bestPractices":0.71,"seo":0.92,"total":286,"carbon":"0.236"},"firstContentfulPaint":5037.250999999999,"speedIndex":7255.484890162542,"largestContentfulPaint":10862.026000000002,"totalBlockingTime":400,"cumulativeLayoutShift":0.003791008843315972,"timeToInteractive":13231.502500000002,"maxPotentialFirstInputDelay":183,"timeToFirstByte":401.003,"weight":{"summary":"90 requests • 4,129 KiB","total":4227737,"image":3170223,"imageCount":22,"script":736436,"scriptCount":33,"document":49830,"font":128332,"fontCount":3,"stylesheet":124341,"stylesheetCount":24,"thirdParty":714903,"thirdPartyCount":47},"axe":{"passes":717,"violations":19}},{"url":"https://theblend.gr/","requestedUrl":"https://theblend.gr/","timestamp":1598811231266,"ranks":{"hundos":74,"performance":79,"accessibility":47,"cumulative":73},"lighthouse":{"version":"6.3.0","performance":0.27,"accessibility":0.88,"bestPractices":0.86,"seo":0.85,"total":286,"carbon":"0.167"},"firstContentfulPaint":7300.469000000003,"speedIndex":10302.26426245244,"largestContentfulPaint":13111.502000000008,"totalBlockingTime":318.5,"cumulativeLayoutShift":0.6848034667968751,"timeToInteractive":12113.164000000004,"maxPotentialFirstInputDelay":154,"timeToFirstByte":980.7180000000001,"weight":{"summary":"86 requests • 2,927 KiB","total":2997317,"image":1421532,"imageCount":33,"script":611422,"scriptCount":26,"document":77062,"font":279764,"fontCount":10,"stylesheet":607537,"stylesheetCount":16,"thirdParty":607790,"thirdPartyCount":33},"axe":{"passes":1038,"violations":30}},{"url":"https://truckercheckin.com/","requestedUrl":"https://truckercheckin.com/","timestamp":1598809542860,"ranks":{"hundos":75,"performance":67,"accessibility":80,"cumulative":74},"lighthouse":{"version":"6.3.0","performance":0.36,"accessibility":0.78,"bestPractices":0.79,"seo":0.91,"total":284,"carbon":"0.0561"},"firstContentfulPaint":1366.1750000000002,"speedIndex":8264.616276130895,"largestContentfulPaint":5805.9895,"totalBlockingTime":1004.5715,"cumulativeLayoutShift":0.4867866210937502,"timeToInteractive":6604.6785,"maxPotentialFirstInputDelay":381,"timeToFirstByte":2295.8,"weight":{"summary":"41 requests • 981 KiB","total":1004282,"image":379662,"imageCount":26,"script":248757,"scriptCount":5,"document":11932,"font":287279,"fontCount":7,"stylesheet":76652,"stylesheetCount":2,"thirdParty":270895,"thirdPartyCount":11},"axe":{"passes":1440,"violations":40}},{"url":"https://www.spitex-moesa.ch/","requestedUrl":"https://www.spitex-moesa.ch/","timestamp":1598811963268,"ranks":{"hundos":76,"performance":76,"accessibility":64,"cumulative":75},"lighthouse":{"version":"6.3.0","performance":0.29,"accessibility":0.85,"bestPractices":0.86,"seo":0.83,"total":283,"carbon":"0.384"},"firstContentfulPaint":6168.6,"speedIndex":10104.812901732177,"largestContentfulPaint":14552.567,"totalBlockingTime":398,"cumulativeLayoutShift":0.0008453030056423612,"timeToInteractive":13515.023000000003,"maxPotentialFirstInputDelay":288.5,"timeToFirstByte":257.785,"weight":{"summary":"93 requests • 6,714 KiB","total":6875468,"image":6142659,"imageCount":39,"script":428993,"scriptCount":34,"document":11749,"font":151027,"fontCount":6,"stylesheet":104766,"stylesheetCount":11,"thirdParty":400708,"thirdPartyCount":28},"axe":{"passes":883,"violations":64}},{"url":"https://experienceglass.com/","requestedUrl":"https://experienceglass.com/","timestamp":1598811600350,"ranks":{"hundos":77,"performance":48,"accessibility":79,"cumulative":76},"lighthouse":{"version":"6.3.0","performance":0.46,"accessibility":0.78,"bestPractices":0.71,"seo":0.84,"total":279,"carbon":"0.357"},"firstContentfulPaint":3278.1710000000003,"speedIndex":5396.962055661768,"largestContentfulPaint":4231.6695,"totalBlockingTime":855,"cumulativeLayoutShift":0.00001080322265625,"timeToInteractive":10013.878999999999,"maxPotentialFirstInputDelay":330,"timeToFirstByte":1017.9580000000001,"weight":{"summary":"88 requests • 6,231 KiB","total":6380580,"image":5352973,"imageCount":29,"script":786728,"scriptCount":27,"document":24414,"font":92218,"fontCount":2,"stylesheet":121201,"stylesheetCount":24,"thirdParty":942023,"thirdPartyCount":17},"axe":{"passes":756,"violations":25}},{"url":"https://rowestrashservice.com/","requestedUrl":"https://rowestrashservice.com/","timestamp":1598809850489,"ranks":{"hundos":78,"performance":89,"accessibility":56,"cumulative":77},"lighthouse":{"version":"6.3.0","performance":0.13,"accessibility":0.86,"bestPractices":0.79,"seo":1,"total":278,"carbon":"0.102"},"firstContentfulPaint":8561.752999999999,"speedIndex":8561.752999999999,"largestContentfulPaint":10694.403999999997,"totalBlockingTime":1177.7305000000006,"cumulativeLayoutShift":0.09779479980468751,"timeToInteractive":11676.144499999999,"maxPotentialFirstInputDelay":340,"timeToFirstByte":351.55499999999995,"weight":{"summary":"43 requests • 1,789 KiB","total":1832151,"image":156498,"imageCount":5,"script":937712,"scriptCount":19,"document":18446,"font":143498,"fontCount":7,"stylesheet":575573,"stylesheetCount":7,"thirdParty":249993,"thirdPartyCount":16},"axe":{"passes":281,"violations":15}},{"url":"https://cardinalsmc.com/","requestedUrl":"https://cardinalsmc.com/","timestamp":1598812946575,"ranks":{"hundos":79,"performance":63,"accessibility":37,"cumulative":78},"lighthouse":{"version":"6.3.0","performance":0.39,"accessibility":0.9,"bestPractices":0.64,"seo":0.85,"total":278,"carbon":"0.0735"},"firstContentfulPaint":5487.764999999999,"speedIndex":9810.364655277288,"largestContentfulPaint":7194.083999999999,"totalBlockingTime":189.5,"cumulativeLayoutShift":0.1675166829427083,"timeToInteractive":9364.994,"maxPotentialFirstInputDelay":195,"timeToFirstByte":922.4619999999999,"weight":{"summary":"93 requests • 1,284 KiB","total":1315321,"image":98134,"imageCount":2,"script":540010,"scriptCount":52,"document":9318,"font":123969,"fontCount":5,"stylesheet":249695,"stylesheetCount":31,"thirdParty":226975,"thirdPartyCount":12},"axe":{"passes":273,"violations":26}},{"url":"https://www.venzi-paganini.ch/it/","requestedUrl":"https://www.venzi-paganini.ch/","timestamp":1598811770778,"ranks":{"hundos":80,"performance":62,"accessibility":94,"cumulative":79},"lighthouse":{"version":"6.3.0","performance":0.4,"accessibility":0.69,"bestPractices":0.93,"seo":0.76,"total":278,"carbon":"0.368"},"firstContentfulPaint":6176.454500000002,"speedIndex":7595.818720221623,"largestContentfulPaint":17042.495000000003,"totalBlockingTime":346.4999999999991,"cumulativeLayoutShift":0.011905232747395833,"timeToInteractive":6754.1445,"maxPotentialFirstInputDelay":325.9999999999991,"timeToFirstByte":209.813,"weight":{"summary":"63 requests • 6,429 KiB","total":6582977,"image":6261434,"imageCount":31,"script":134647,"scriptCount":15,"document":9465,"font":85774,"fontCount":3,"stylesheet":91054,"stylesheetCount":12,"thirdParty":14543,"thirdPartyCount":3},"axe":{"passes":385,"violations":28}},{"url":"https://builditinsandiego.com/","requestedUrl":"https://builditinsandiego.com/","timestamp":1598811586532,"ranks":{"hundos":69,"performance":60,"accessibility":85,"cumulative":80},"lighthouse":{"version":"6.3.0","performance":0.41,"accessibility":0.76,"bestPractices":0.79,"seo":0.82,"total":290,"carbon":"0.0972"},"firstContentfulPaint":2939.4719999999998,"speedIndex":7216.849779946624,"largestContentfulPaint":5556.4265000000005,"totalBlockingTime":672.6710000000003,"cumulativeLayoutShift":1.298199205186632,"timeToInteractive":5825.091,"maxPotentialFirstInputDelay":646,"timeToFirstByte":1864.041,"weight":{"summary":"27 requests • 1,699 KiB","total":1739353,"image":1176144,"imageCount":10,"script":219399,"scriptCount":3,"document":21295,"font":250359,"fontCount":8,"stylesheet":71990,"stylesheetCount":4,"thirdParty":69068,"thirdPartyCount":6},"axe":{"passes":924,"violations":43}},{"url":"https://presconnect.co.za/","requestedUrl":"https://presconnect.co.za/","timestamp":1598809814608,"ranks":{"hundos":81,"performance":72,"accessibility":77,"cumulative":81},"lighthouse":{"version":"6.3.0","performance":0.33,"accessibility":0.8,"bestPractices":0.64,"seo":1,"total":277,"carbon":"0.373"},"firstContentfulPaint":4128.814,"speedIndex":8176.922392850296,"largestContentfulPaint":13231.056999999999,"totalBlockingTime":568.3104999999987,"cumulativeLayoutShift":0.06673325602213542,"timeToInteractive":9433.430999999997,"maxPotentialFirstInputDelay":517,"timeToFirstByte":511.168,"weight":{"summary":"70 requests • 6,516 KiB","total":6672543,"image":5688815,"imageCount":10,"script":682038,"scriptCount":26,"document":12899,"font":156343,"fontCount":3,"stylesheet":123165,"stylesheetCount":23,"thirdParty":927752,"thirdPartyCount":30},"axe":{"passes":497,"violations":53}},{"url":"https://www.cvhsinc.org/","requestedUrl":"https://www.cvhsinc.org/","timestamp":1598810152233,"ranks":{"hundos":82,"performance":61,"accessibility":76,"cumulative":82},"lighthouse":{"version":"6.3.0","performance":0.4,"accessibility":0.8,"bestPractices":0.64,"seo":0.92,"total":276,"carbon":"0.0975"},"firstContentfulPaint":3631.9099999999994,"speedIndex":6672.7883267449,"largestContentfulPaint":8207.595000000001,"totalBlockingTime":527.5000000000005,"cumulativeLayoutShift":0.28060474310980904,"timeToInteractive":7114.73,"maxPotentialFirstInputDelay":408.0000000000009,"timeToFirstByte":446.829,"weight":{"summary":"106 requests • 1,704 KiB","total":1744495,"image":1295948,"imageCount":45,"script":287235,"scriptCount":24,"document":11756,"font":81671,"fontCount":5,"stylesheet":67206,"stylesheetCount":29,"thirdParty":116896,"thirdPartyCount":16},"axe":{"passes":735,"violations":36}},{"url":"https://www.lisabrawn.com/","requestedUrl":"https://www.lisabrawn.com/","timestamp":1598809469049,"ranks":{"hundos":83,"performance":98,"accessibility":46,"cumulative":83},"lighthouse":{"version":"6.3.0","performance":0.06,"accessibility":0.88,"bestPractices":0.86,"seo":0.89,"total":269,"carbon":"0.540"},"firstContentfulPaint":5459.370000000001,"speedIndex":20666.031452851545,"largestContentfulPaint":51868.89100000001,"totalBlockingTime":2417.5,"cumulativeLayoutShift":0.28194444444444444,"timeToInteractive":31646.323000000004,"maxPotentialFirstInputDelay":3029,"timeToFirstByte":1666.8380000000002,"weight":{"summary":"72 requests • 9,444 KiB","total":9671024,"image":8863147,"imageCount":32,"script":543222,"scriptCount":20,"document":19395,"font":85192,"fontCount":8,"stylesheet":146693,"stylesheetCount":10,"thirdParty":715371,"thirdPartyCount":15},"axe":{"passes":742,"violations":27}},{"url":"https://www.smri-mecanique.com/","requestedUrl":"https://www.smri-mecanique.com/","timestamp":1598811062917,"ranks":{"hundos":84,"performance":53,"accessibility":91,"cumulative":84},"lighthouse":{"version":"6.3.0","performance":0.44,"accessibility":0.71,"bestPractices":0.71,"seo":0.82,"total":268,"carbon":"0.123"},"firstContentfulPaint":2969.945,"speedIndex":5672.655264524776,"largestContentfulPaint":7155.4925,"totalBlockingTime":588.0000000000005,"cumulativeLayoutShift":0.04054121229383681,"timeToInteractive":8671.717,"maxPotentialFirstInputDelay":189,"timeToFirstByte":263.60400000000004,"weight":{"summary":"89 requests • 2,150 KiB","total":2201491,"image":1531823,"imageCount":54,"script":560959,"scriptCount":26,"document":10453,"font":23528,"fontCount":1,"stylesheet":74728,"stylesheetCount":7,"thirdParty":403716,"thirdPartyCount":15},"axe":{"passes":388,"violations":57}},{"url":"https://www.papercutsart.com/","requestedUrl":"https://www.papercutsart.com/","timestamp":1598810184960,"ranks":{"hundos":85,"performance":66,"accessibility":95,"cumulative":85},"lighthouse":{"version":"6.3.0","performance":0.36,"accessibility":0.67,"bestPractices":0.71,"seo":0.92,"total":266,"carbon":"0.222"},"firstContentfulPaint":3424.618,"speedIndex":6053.932185642595,"largestContentfulPaint":9135.6225,"totalBlockingTime":1081.0009999999997,"cumulativeLayoutShift":0.054029825846354164,"timeToInteractive":5623.374,"maxPotentialFirstInputDelay":797,"timeToFirstByte":434.09499999999997,"weight":{"summary":"85 requests • 3,880 KiB","total":3972938,"image":3479321,"imageCount":27,"script":212736,"scriptCount":25,"document":10732,"font":161376,"fontCount":7,"stylesheet":108773,"stylesheetCount":25,"thirdParty":101790,"thirdPartyCount":10},"axe":{"passes":767,"violations":29}},{"url":"https://tiahabitat.org/","requestedUrl":"https://tiahabitat.org/","timestamp":1598812728145,"ranks":{"hundos":86,"performance":96,"accessibility":48,"cumulative":86},"lighthouse":{"version":"6.3.0","performance":0.07,"accessibility":0.88,"bestPractices":0.79,"seo":0.92,"total":266,"carbon":"0.214"},"firstContentfulPaint":10150.385000000002,"speedIndex":10150.385000000002,"largestContentfulPaint":14919.424500000005,"totalBlockingTime":1986.999999999999,"cumulativeLayoutShift":0.12491861979166666,"timeToInteractive":16342.554500000002,"maxPotentialFirstInputDelay":419,"timeToFirstByte":517.72,"weight":{"summary":"48 requests • 3,742 KiB","total":3831700,"image":1699402,"imageCount":9,"script":1334667,"scriptCount":20,"document":20589,"font":93124,"fontCount":4,"stylesheet":676923,"stylesheetCount":9,"thirdParty":265069,"thirdPartyCount":14},"axe":{"passes":309,"violations":33}},{"url":"https://www.summitlibrary.org/","requestedUrl":"https://summitlibrary.org/","timestamp":1598813028580,"ranks":{"hundos":87,"performance":97,"accessibility":61,"cumulative":87},"lighthouse":{"version":"6.3.0","performance":0.07,"accessibility":0.86,"bestPractices":0.79,"seo":0.92,"total":264,"carbon":"0.738"},"firstContentfulPaint":11435.518000000002,"speedIndex":20340.786491932184,"largestContentfulPaint":24688.890999999996,"totalBlockingTime":1102,"cumulativeLayoutShift":0.22961361355251736,"timeToInteractive":36304.75,"maxPotentialFirstInputDelay":367,"timeToFirstByte":529.877,"weight":{"summary":"93 requests • 12,895 KiB","total":13204650,"image":10378893,"imageCount":22,"script":1758609,"scriptCount":37,"document":114836,"font":199327,"fontCount":7,"stylesheet":745890,"stylesheetCount":19,"thirdParty":736521,"thirdPartyCount":48},"axe":{"passes":1116,"violations":92}},{"url":"https://dauphintelecom.fr/","requestedUrl":"http://dauphintelecom.fr/","timestamp":1598813200484,"ranks":{"hundos":88,"performance":94,"accessibility":23,"cumulative":88},"lighthouse":{"version":"6.3.0","performance":0.08,"accessibility":0.94,"bestPractices":0.64,"seo":0.97,"total":263,"carbon":"0.204"},"firstContentfulPaint":6792.279500000001,"speedIndex":14136.113258990104,"largestContentfulPaint":11819.117999999995,"totalBlockingTime":1077.0000000000018,"cumulativeLayoutShift":0.2773026258680556,"timeToInteractive":20275.04050000001,"maxPotentialFirstInputDelay":463,"timeToFirstByte":141.549,"weight":{"summary":"174 requests • 3,564 KiB","total":3649332,"image":2332382,"imageCount":64,"script":976135,"scriptCount":42,"document":55405,"font":92244,"fontCount":22,"stylesheet":192015,"stylesheetCount":38,"thirdParty":887582,"thirdPartyCount":23},"axe":{"passes":959,"violations":122}},{"url":"https://mahindramalalane.co.za/","requestedUrl":"https://mahindramalalane.co.za/","timestamp":1598810258187,"ranks":{"hundos":89,"performance":86,"accessibility":86,"cumulative":89},"lighthouse":{"version":"6.3.0","performance":0.16,"accessibility":0.75,"bestPractices":0.71,"seo":1,"total":262,"carbon":"0.350"},"firstContentfulPaint":4013.9280000000003,"speedIndex":9087.977368016978,"largestContentfulPaint":16252.298999999999,"totalBlockingTime":1364.5,"cumulativeLayoutShift":0.3224679633246528,"timeToInteractive":12764.232,"maxPotentialFirstInputDelay":407,"timeToFirstByte":1333.987,"weight":{"summary":"90 requests • 6,114 KiB","total":6260231,"image":5144607,"imageCount":20,"script":794966,"scriptCount":28,"document":29732,"font":160722,"fontCount":4,"stylesheet":118052,"stylesheetCount":24,"thirdParty":912599,"thirdPartyCount":40},"axe":{"passes":389,"violations":21}},{"url":"https://www.yannanderson.com/en/","requestedUrl":"https://www.yannanderson.com/","timestamp":1598812115470,"ranks":{"hundos":90,"performance":91,"accessibility":54,"cumulative":90},"lighthouse":{"version":"6.3.0","performance":0.1,"accessibility":0.87,"bestPractices":0.79,"seo":0.85,"total":261,"carbon":"0.569"},"firstContentfulPaint":5862.288,"speedIndex":11938.696243293893,"largestContentfulPaint":11847.216999999999,"totalBlockingTime":1670.5550000000003,"cumulativeLayoutShift":0.00016859944661458333,"timeToInteractive":16166.6145,"maxPotentialFirstInputDelay":577,"timeToFirstByte":688.215,"weight":{"summary":"214 requests • 9,950 KiB","total":10188811,"image":8212234,"imageCount":141,"script":1040253,"scriptCount":55,"document":48156,"font":183192,"fontCount":5,"stylesheet":532905,"stylesheetCount":2,"thirdParty":137820,"thirdPartyCount":9},"axe":{"passes":227,"violations":10}},{"url":"https://www.regionemoesa.ch/","requestedUrl":"https://www.regionemoesa.ch/","timestamp":1598811802597,"ranks":{"hundos":91,"performance":85,"accessibility":92,"cumulative":91},"lighthouse":{"version":"6.3.0","performance":0.17,"accessibility":0.7,"bestPractices":0.86,"seo":0.84,"total":257,"carbon":"0.198"},"firstContentfulPaint":4151.561000000001,"speedIndex":9052.376169870331,"largestContentfulPaint":8807.8765,"totalBlockingTime":1021,"cumulativeLayoutShift":0.3710950927734375,"timeToInteractive":15477.6375,"maxPotentialFirstInputDelay":519,"timeToFirstByte":279.54099999999994,"weight":{"summary":"132 requests • 3,455 KiB","total":3537978,"image":2279709,"imageCount":57,"script":866897,"scriptCount":39,"document":30085,"font":145546,"fontCount":8,"stylesheet":195221,"stylesheetCount":23,"thirdParty":800296,"thirdPartyCount":36},"axe":{"passes":1051,"violations":55}},{"url":"https://pestifoci.hu/","requestedUrl":"https://pestifoci.hu/","timestamp":1598810087431,"ranks":{"hundos":92,"performance":87,"accessibility":65,"cumulative":92},"lighthouse":{"version":"6.3.0","performance":0.16,"accessibility":0.84,"bestPractices":0.71,"seo":0.83,"total":254,"carbon":"0.231"},"firstContentfulPaint":8561.562,"speedIndex":10784.429565122351,"largestContentfulPaint":13602.6185,"totalBlockingTime":732.0000000000018,"cumulativeLayoutShift":0.05958232964409722,"timeToInteractive":15789.819,"maxPotentialFirstInputDelay":366,"timeToFirstByte":1368.059,"weight":{"summary":"260 requests • 4,043 KiB","total":4139601,"image":1966585,"imageCount":173,"script":1178233,"scriptCount":44,"document":70209,"font":233106,"fontCount":8,"stylesheet":665028,"stylesheetCount":19,"thirdParty":925596,"thirdPartyCount":68},"axe":{"passes":1272,"violations":12}},{"url":"https://www.yanallafarms.com.au/","requestedUrl":"https://www.yanallafarms.com.au/","timestamp":1598811635136,"ranks":{"hundos":93,"performance":88,"accessibility":73,"cumulative":93},"lighthouse":{"version":"6.3.0","performance":0.16,"accessibility":0.82,"bestPractices":0.64,"seo":0.91,"total":253,"carbon":"0.245"},"firstContentfulPaint":1066.1319999999998,"speedIndex":17223.4852093714,"largestContentfulPaint":19907.474,"totalBlockingTime":5602.499999999998,"cumulativeLayoutShift":0.5951302625868055,"timeToInteractive":22820.610999999997,"maxPotentialFirstInputDelay":3558.999999999998,"timeToFirstByte":4082.0149999999994,"weight":{"summary":"60 requests • 4,276 KiB","total":4378677,"image":1722459,"imageCount":14,"script":777943,"scriptCount":16,"document":54998,"font":1721658,"fontCount":23,"stylesheet":96299,"stylesheetCount":2,"thirdParty":388833,"thirdPartyCount":24},"axe":{"passes":1083,"violations":54}},{"url":"http://www.assports.com.br/","requestedUrl":"http://www.assports.com.br/","timestamp":1598809363951,"ranks":{"hundos":94,"performance":90,"accessibility":51,"cumulative":94},"lighthouse":{"version":"6.3.0","performance":0.12,"accessibility":0.88,"bestPractices":0.57,"seo":0.84,"total":241,"carbon":"0.165"},"firstContentfulPaint":4002.107,"speedIndex":10763.31464991241,"largestContentfulPaint":13926.579500000002,"totalBlockingTime":1202.5,"cumulativeLayoutShift":1.0531451212565104,"timeToInteractive":15945.545999999998,"maxPotentialFirstInputDelay":458,"timeToFirstByte":760.893,"weight":{"summary":"124 requests • 2,879 KiB","total":2948577,"image":1856478,"imageCount":51,"script":705892,"scriptCount":38,"document":32065,"font":162253,"fontCount":9,"stylesheet":177000,"stylesheetCount":20,"thirdParty":747158,"thirdPartyCount":61},"axe":{"passes":1195,"violations":73}},{"url":"https://poblib.org/","requestedUrl":"http://poblib.org/","timestamp":1598813014061,"ranks":{"hundos":95,"performance":92,"accessibility":11,"cumulative":95},"lighthouse":{"version":"6.3.0","performance":0.1,"accessibility":0.96,"bestPractices":0.57,"seo":0.75,"total":238,"carbon":"1.08"},"firstContentfulPaint":4892.332,"speedIndex":12203.778762716933,"largestContentfulPaint":6574.691,"totalBlockingTime":4060.5000000000055,"cumulativeLayoutShift":0.2511713121202257,"timeToInteractive":44279.89950000002,"maxPotentialFirstInputDelay":770.0000000000073,"timeToFirstByte":161.601,"weight":{"summary":"225 requests • 18,872 KiB","total":19324710,"image":14000655,"imageCount":112,"script":4652628,"scriptCount":47,"document":69921,"font":128722,"fontCount":5,"stylesheet":310839,"stylesheetCount":18,"thirdParty":18244956,"thirdPartyCount":167},"axe":{"passes":505,"violations":32}},{"url":"https://rutadelvinoyecla.com/en/","requestedUrl":"https://rutadelvinoyecla.com/","timestamp":1598809650593,"ranks":{"hundos":96,"performance":93,"accessibility":88,"cumulative":96},"lighthouse":{"version":"6.3.0","performance":0.08,"accessibility":0.75,"bestPractices":0.57,"seo":0.75,"total":215,"carbon":"0.215"},"firstContentfulPaint":5321.764,"speedIndex":13282.295719673177,"largestContentfulPaint":16107.889000000003,"totalBlockingTime":1581,"cumulativeLayoutShift":0.4602741292317708,"timeToInteractive":13680.389000000003,"maxPotentialFirstInputDelay":572,"timeToFirstByte":3203.1910000000003,"weight":{"summary":"89 requests • 3,764 KiB","total":3854145,"image":2646828,"imageCount":61,"script":500340,"scriptCount":10,"document":43603,"font":440864,"fontCount":3,"stylesheet":221899,"stylesheetCount":9,"thirdParty":243630,"thirdPartyCount":13},"axe":{"passes":1506,"violations":82}},{"url":"https://hatzitentes.gr/","requestedUrl":"https://hatzitentes.gr/","timestamp":1598809507940,"ranks":{"hundos":98,"performance":78,"accessibility":98,"cumulative":97},"lighthouse":{"version":"6.3.0","performance":0.27,"accessibility":null,"bestPractices":0.79,"seo":0.99,"total":205,"carbon":"0.167"},"firstContentfulPaint":3214.5520000000006,"speedIndex":6787.475177942246,"largestContentfulPaint":14224.019999999999,"totalBlockingTime":933,"cumulativeLayoutShift":0.26530299207899305,"timeToInteractive":10901.639,"maxPotentialFirstInputDelay":398,"timeToFirstByte":470.43500000000006,"weight":{"summary":"57 requests • 2,926 KiB","total":2996147,"image":1870788,"imageCount":12,"script":893802,"scriptCount":27,"document":20875,"font":92196,"fontCount":2,"stylesheet":116220,"stylesheetCount":11,"thirdParty":924867,"thirdPartyCount":28},"axe":{"passes":528,"violations":20}},{"url":"https://www.marcq-en-baroeul.org/","requestedUrl":"https://www.marcq-en-baroeul.org/","timestamp":1598812640612,"ranks":{"hundos":97,"performance":95,"accessibility":97,"cumulative":98},"lighthouse":{"version":"6.3.0","performance":0.08,"accessibility":0.57,"bestPractices":0.57,"seo":0.83,"total":205,"carbon":"1.06"},"firstContentfulPaint":5331.384000000001,"speedIndex":14321.629805336128,"largestContentfulPaint":15611.779999999992,"totalBlockingTime":3361.9999999999964,"cumulativeLayoutShift":0.1656728990342882,"timeToInteractive":26535.942306503282,"maxPotentialFirstInputDelay":891,"timeToFirstByte":1299.491,"weight":{"summary":"281 requests • 18,447 KiB","total":18889367,"image":7065093,"imageCount":86,"script":1750712,"scriptCount":84,"document":139768,"font":183168,"fontCount":10,"stylesheet":535171,"stylesheetCount":43,"thirdParty":14157631,"thirdPartyCount":197},"axe":{"passes":1235,"violations":182}},{"url":"https://www.blockfer.com/","error":"Unknown error."},{"url":"https://www.dellafit.com.br/","error":"Unknown error."},{"url":"https://electrichairsociety.com/","error":"Unknown error."}]